Workbook
Name ____CSA8: '[1]INPUT(덕도방향-시점)'!#REF!
Name ____CSA8: '[1]INPUT(덕도방향-시점)'!#REF!
Name ____HSH1: #REF!
Name ____HSH1: #REF!
Name ____HSH2: #REF!
Name ____NP1: #REF!
Name ____NP2: #REF!
Name ____NSH1: #REF!
Name ____NSH2: #REF!
Name ____pl1: #REF!
Name ____PL2: #REF!
Name ____PL3: #REF!
Name ____SBB1: #REF!
Name ____SBB2: #REF!
Name ____SBB3: #REF!
Name ____SBB4: #REF!
Name ____SBB5: #REF!
Name ____SHH1: #REF!
Name ____SHH2: #REF!
Name ____SHH3: #REF!
Name ____TW2: #REF!
Name ___CSA8: '[1]INPUT(덕도방향-시점)'!#REF!
Name ___CSA8: '[1]INPUT(덕도방향-시점)'!#REF!
Name ___HSH1: #REF!
Name ___HSH2: #REF!
Name ___NP1: #REF!
Name ___NP2: #REF!
Name ___NSH1: #REF!
Name ___NSH2: #REF!
Name ___pl1: #REF!
Name ___PL2: #REF!
Name ___PL3: #REF!
Name ___SBB1: #REF!
Name ___SBB2: #REF!
Name ___SBB3: #REF!
Name ___SBB4: #REF!
Name ___SBB5: #REF!
Name ___SHH1: #REF!
Name ___SHH2: #REF!
Name ___SHH3: #REF!
Name ___TW2: #REF!
Name __CSA8: '[1]INPUT(덕도방향-시점)'!#REF!
Name __CSA8: '[1]INPUT(덕도방향-시점)'!#REF!
Name __HSH1: #REF!
Name __HSH2: #REF!
Name __NP1: #REF!
Name __NP2: #REF!
Name __NSH1: #REF!
Name __NSH2: #REF!
Name __pl1: #REF!
Name __PL2: #REF!
Name __PL3: #REF!
Name __SBB1: #REF!
Name __SBB2: #REF!
Name __SBB3: #REF!
Name __SBB4: #REF!
Name __SBB5: #REF!
Name __SHH1: #REF!
Name __SHH2: #REF!
Name __SHH3: #REF!

Sheet 분양개요
A2: 2. 분양개요
A4: 1. 분양수입금
A5: 구 분 | B5: 평형/층별 | D5: 분양단가 | F5: 분양금 | H5: 세대수/평 | J5: 총분양금 | L5: 비고
A6: 아파트A | B6: =I50 -> 25.285975 | C6: 평형 | D6: 14000 | F6: =B6*D6 -> 354003.65 | H6: 336 | J6: =F6*H6 -> 1.1894523e+08
A7: 아파트b | B7: =I51 -> 34.542475 | C7: 평형 | D7: 14000 | F7: =B7*D7 -> 483594.65 | H7: =B51 -> 1549 | J7: =F7*H7 -> 7.4908811e+08
A8: 아파트C | B8: =I52 -> 0 | C8: 평형 | F8: =B8*D8 -> 0 | J8: =F8*H8 -> 0
A9: 아파트D | B9: =I53 -> 0 | C9: 평형 | F9: =B9*D9 -> 0 | J9: =SUM(F9*H9) -> 0
A10: 아파트E | B10: =I54 -> 0 | C10: 평형 | F10: =B10*D10 -> 0 | J10: =SUM(F10*H10) -> 0
A11: 아파트F | B11: =I55 -> 0 | C11: 평형 | F11: =B11*D11 -> 0 | H11: =SUM(B55) -> 0 | J11: =SUM(F11*H11) -> 0
A12: 아파트H | B12: =I56 -> 0 | C12: 평형 | F12: =B12*D12 -> 0 | H12: =SUM(B56) -> 0 | J12: =SUM(F12*H12) -> 0
A13: 아파트G | B13: =I57 -> 0 | C13: 평형 | F13: =B13*D13 -> 0 | H13: =SUM(B57) -> 0 | J13: =SUM(F13*H13) -> 0
A14: 아파트G | B14: =I58 -> 0 | C14: 평형 | F14: =B14*D14 -> 0 | H14: =SUM(B58) -> 0 | J14: =SUM(F14*H14) -> 0
B15: 소계 | H15: =SUM(H6:I14) -> 1885 | J15: =SUM(J6:K14) -> 8.6803334e+08
A16: 오피스텔 | B16: =SUM(M67) -> 0 | C16: 평형 | F16: =SUM(B16*D16) -> 0 | H16: =SUM(B62) -> 0 | J16: =SUM(F16*H16) -> 0
B17: =SUM(M63) -> 0 | C17: 평형 | F17: =SUM(B17*D17) -> 0 | H17: =SUM(B63) -> 0 | J17: =SUM(F17*H17) -> 0
B18: =SUM(M64) -> 0 | C18: 평형 | F18: =SUM(B18*D18) -> 0 | H18: =SUM(B64) -> 0 | J18: =SUM(F18*H18) -> 0
B19: =SUM(M65) -> 0 | C19: 평형 | F19: =SUM(B19*D19) -> 0 | H19: =SUM(B65) -> 0 | J19: =SUM(F19*H19) -> 0
B20: 소계 | H20: =SUM(H16:I19) -> 0 | J20: =SUM(J16:K19) -> 0
A21: 근생시설 | B21: =M69 -> 201.0536 | C21: 평 | D21: 20000 | F21: =B21*D21 -> 4021072 | H21: 1 | J21: =SUM(F21) -> 4021072
B22: =M70 -> 193.8783 | C22: 평 | D22: 20000 | F22: =B22*D22 -> 3877566 | H22: 1 | J22: =SUM(F22) -> 3877566
F23: =SUM(H23*D23) -> 0 | H23: =A71 -> 0 | J23: =SUM(F23) -> 0
F24: =SUM(H24*D24) -> 0 | H24: =A72 -> 0 | J24: =SUM(F24) -> 0
B25: 소계 | H25: =SUM(H21:I24) -> 2 | J25: =SUM(J21:K24) -> 7898638
A26: 소 계 | J26: =SUM(J25,J20,J15) -> 8.7593198e+08
A27: 매출부가세 | J27: =H45 -> 783047.96
A28: 합 계 | J28: =SUM(J26:K27) -> 8.7671503e+08
A30: 2. 매출부가세 내역 | K30: 3. 공사비 과세비율(연면적기준)
A31: 지상면적 | B31: 비 율 | D31: 대지비 안분 | F31: 건물가 | H31: 부가세 | K31: 구 분 | L31: 면 적 | M31: 비 율
A32: =Q50 -> 12142.931 | B32: =A32/$A$45 -> 0.13510093 | D32: =$D$45*B32 -> 2095660.2 | F32: =J6-D32 -> 1.1684957e+08 | H32: 0 | K32: 과세면적 | L32: =R75 -> 201.0536 | M32: =L32/L34 -> 0.0022417361
A33: =Q51 -> 77342.577 | B33: =A33/$A$45 -> 0.8605051 | D33: =$D$45*B33 -> 13347993 | F33: =J7-D33 -> 7.3574012e+08 | H33: 0 | K33: 비과세면적 | L33: =S75 -> 89485.508 | M33: =L33/L34 -> 0.99775826
A34: =Q52 -> 0 | B34: =A34/$A$45 -> 0 | D34: =$D$45*B34 -> 0 | F34: =J8-D34 -> 0 | H34: 0 | K34: 면적합계 | L34: =L32+L33 -> 89686.561 | M34: =M32+M33 -> 1
A35: =Q53 -> 0 | B35: =A35/$A$45 -> 0 | D35: =$D$45*B35 -> 0 | F35: =J9-D35 -> 0 | H35: 0 | L35: =L34=Q75 -> FALSE | M35: =M34=100% -> TRUE
A36: =Q54 -> 0 | B36: =A36/$A$45 -> 0 | D36: =$D$45*B36 -> 0 | F36: =J10-D36 -> 0 | H36: =F36*0.1 -> 0
A37: =B11*H11 -> 0 | B37: =A37/$A$45 -> 0 | D37: =$D$45*B37 -> 0 | F37: =J11-D37 -> 0 | H37: =F37/11*0 -> 0
A38: =B12*H12 -> 0 | B38: =A38/$A$45 -> 0 | D38: =$D$45*B38 -> 0 | F38: =J12-D38 -> 0 | H38: =F38/11*0 -> 0
A39: =B13*H13 -> 0 | B39: =A39/$A$45 -> 0 | D39: =$D$45*B39 -> 0 | F39: =J13-D39 -> 0 | H39: =F39/11*0 -> 0
A40: =B14*H14 -> 0 | B40: =A40/$A$45 -> 0 | D40: =$D$45*B40 -> 0 | F40: =J14-D40 -> 0 | H40: =F40/11*0 -> 0
A41: =Q69 -> 201.0536 | B41: =A41/$A$45 -> 0.0022369005 | D41: =$D$45*B41 -> 34698.38 | F41: =J21-D41 -> 3986373.6 | H41: =F41*0.1 -> 398637.36 | J41: 상가
A42: =Q70 -> 193.8783 | B42: =A42/$A$45 -> 0.0021570689 | D42: =$D$45*B42 -> 33460.047 | F42: =J22-D42 -> 3844106 | H42: =F42*0.1 -> 384410.6
B43: =A43/$A$45 -> 0 | D43: =$D$45*B43 -> 0 | F43: =J23-D43 -> 0 | H43: =F43*0.1 -> 0
B44: =A44/$A$45 -> 0 | D44: =$D$45*B44 -> 0 | F44: =J24-D44 -> 0 | H44: =F44*0.1 -> 0
A45: =SUM(A32:A44) -> 89880.44 | B45: =SUM(B32:B44) -> 1 | D45: 15511812 | F45: =SUM(F32:G44) -> 8.6042017e+08 | H45: =SUM(H32:I44) -> 783047.96
I46: =H45/J26 -> 0.00089395978
A47: 3. 평형개요
A48: ■ 아파트 분양면적표
A49: 평형 | B49: 세대수 | D49: 전용면적 | F49: 주거공용면적 | H49: 공급면적 | J49: 기타공유/지하주차장 | L49: 계약면적 | N49: 비고 | Q49: 분양면적계 | R49: 과세면적 | S49: 비과세면적 | U49: 공사비 | V49: 부가세 | W49: 합계
A50: =B6 -> 25.285975 | B50: 336 | D50: 59.92 | E50: =D50*0.3025 -> 18.1258 | F50: 23.67 | G50: =F50*0.3025 -> 7.160175 | H50: 83.59 | I50: =SUM(H50*0.3025) -> 25.285975 | J50: 35.88 | K50: =J50*0.3025 -> 10.8537 | L50: =SUM(H50,J50) -> 119.47 | M50: =SUM(L50*0.3025) -> 36.139675 | N50: =B50*I50/$I$59 -> 0.13702841 | P50: =IF(D50>85,"과세","비과세") -> 비과세 | Q50: =B50*M50 -> 12142.931 | R50: =IF(P50="과세",Q50, 0) -> 0 | S50: =Q50-R50 -> 12142.931 | U50: =M50*B50*사업수지표!$BC$33 -> 59500361 | V50: =U50*10%*0 -> 0 | W50: =SUM(U50:V50) -> 59500361
A51: =B7 -> 34.542475 | B51: 1549 | D51: 84.95 | E51: =D51*0.3025 -> 25.697375 | F51: 29.24 | G51: =F51*0.3025 -> 8.8451 | H51: 114.19 | I51: =SUM(H51*0.3025) -> 34.542475 | J51: 50.87 | K51: =J51*0.3025 -> 15.388175 | L51: =SUM(H51,J51) -> 165.06 | M51: =SUM(L51*0.3025) -> 49.93065 | N51: =B51*I51/$I$59 -> 0.86297159 | P51: =IF(D51>85,"과세","비과세") -> 비과세 | Q51: =B51*M51 -> 77342.577 | R51: =IF(P51="과세",Q51, 0) -> 0 | S51: =Q51-R51 -> 77342.577 | U51: =M51*B51*사업수지표!$BC$33 -> 3.7897863e+08 | V51: =U51*10%*0 -> 0 | W51: =SUM(U51:V51) -> 3.7897863e+08
A52: =B8 -> 0 | E52: =D52*0.3025 -> 0 | G52: =F52*0.3025 -> 0 | H52: =SUM(D52,F52) -> 0 | I52: =SUM(H52*0.3025) -> 0 | K52: =J52*0.3025 -> 0 | L52: =SUM(H52,J52) -> 0 | M52: =SUM(L52*0.3025) -> 0 | N52: =B52*I52/$I$59 -> 0 | P52: =IF(D52>85,"과세","비과세") -> 비과세 | Q52: =B52*M52 -> 0 | R52: =IF(P52="과세",Q52, 0) -> 0 | S52: =Q52-R52 -> 0 | U52: =M52*B52*사업수지표!$BC$33 -> 0 | V52: =U52*10%*0 -> 0 | W52: =SUM(U52:V52) -> 0
A53: =B9 -> 0 | G53: =F53*0.3025 -> 0 | H53: =SUM(D53,F53) -> 0 | I53: =SUM(H53*0.3025) -> 0 | K53: =J53*0.3025 -> 0 | L53: =SUM(H53,J53) -> 0 | M53: =SUM(L53*0.3025) -> 0 | N53: =B53*I53/$I$59 -> 0 | P53: =IF(D53>85,"과세","비과세") -> 비과세 | Q53: =B53*M53 -> 0 | R53: =IF(P53="과세",Q53, 0) -> 0 | S53: =Q53-R53 -> 0 | U53: =M53*B53*사업수지표!$BC$33 -> 0 | V53: =U53*10%*0 -> 0 | W53: =SUM(U53:V53) -> 0
A54: =B10 -> 0 | E54: =D54*0.3025 -> 0 | G54: =F54*0.3025 -> 0 | H54: =SUM(D54,F54) -> 0 | I54: =SUM(H54*0.3025) -> 0 | K54: =J54*0.3025 -> 0 | L54: =SUM(H54,J54) -> 0 | M54: =SUM(L54*0.3025) -> 0 | N54: =B54*I54/$I$59 -> 0 | P54: =IF(D54>85,"과세","비과세") -> 비과세 | Q54: =B54*M54 -> 0 | R54: =IF(P54="과세",Q54, 0) -> 0 | S54: =Q54-R54 -> 0 | U54: =M54*B54*사업수지표!$BC$33 -> 0 | V54: =U54*10% -> 0 | W54: =SUM(U54:V54) -> 0
P55: 비과세 | Q55: =B55*M55 -> 0 | R55: =IF(P55="과세",Q55, 0) -> 0 | S55: =Q55-R55 -> 0 | U55: =M55*B55*사업수지표!$BC$33 -> 0 | V55: =U55*10%*0 -> 0 | W55: =SUM(U55:V55) -> 0
P56: 비과세 | Q56: =B56*M56 -> 0 | R56: =IF(P56="과세",Q56, 0) -> 0 | S56: =Q56-R56 -> 0 | U56: =M56*B56*사업수지표!$BC$33 -> 0 | V56: =U56*10%*0 -> 0 | W56: =SUM(U56:V56) -> 0
P57: 비과세 | Q57: =B57*M57 -> 0 | R57: =IF(P57="과세",Q57, 0) -> 0 | S57: =Q57-R57 -> 0 | U57: =M57*B57*사업수지표!$BC$33 -> 0 | V57: =U57*10%*0 -> 0 | W57: =SUM(U57:V57) -> 0
P58: 비과세 | Q58: =B58*M58 -> 0 | R58: =IF(P58="과세",Q58, 0) -> 0 | S58: =Q58-R58 -> 0 | U58: =M58*B58*사업수지표!$BC$33 -> 0 | V58: =U58*10%*0 -> 0 | W58: =SUM(U58:V58) -> 0
A59: 소계 | B59: =SUM(B50:B58) -> 1885 | D59: =$B$50*D50+$B$51*D51+$B$52*D52+$B$53*D53+$B$54*D54+$B$55*D55+$B$56*D56+$B$57*D57+$B$58*D58 -> 151720.67 | E59: =D59*0.3025 -> 45895.503 | F59: =$B$50*F50+$B$51*F51+$B$52*F52+$B$53*F53+$B$54*F54+$B$55*F55+$B$56*F56+$B$57*F57+$B$58*F58 -> 53245.88 | G59: =F59*0.3025 -> 16106.879 | H59: =$B$50*H50+$B$51*H51+$B$52*H52+$B$53*H53+$B$54*H54+$B$55*H55+$B$56*H56+$B$57*H57+$B$58*H58 -> 204966.55 | I59: =H59*0.3025 -> 62002.381 | J59: =$B$50*J50+$B$51*J51+$B$52*J52+$B$53*J53+$B$54*J54+$B$55*J55+$B$56*J56+$B$57*J57-0.094 -> 90853.216 | K59: =J59*0.3025 -> 27483.098 | L59: =$B$50*L50+$B$51*L51+$B$52*L52+$B$53*L53+$B$54*L54+$B$55*L55+$B$56*L56+$B$57*L57-0.094 -> 295819.77 | M59: =L59*0.3025 -> 89485.479 | Q59: =SUM(Q50:Q58) -> 89485.508 | R59: =SUM(R50:R58) -> 0 | S59: =SUM(S50:S58) -> 89485.508 | U59: =SUM(U50:U58) -> 4.3847899e+08 | V59: =SUM(V50:V58) -> 0 | W59: =SUM(W50:W58) -> 4.3847899e+08
A60: ■ 오피스텔 분양면적표
A61: 평형 | B61: 세대수 | D61: 전용면적 | F61: 주거공유 | H61: 분양면적 | J61: 기타공유 | L61: 계약면적 | N61: 비고
E62: =SUM(D62*0.3025) -> 0 | G62: =SUM(F62*0.3025) -> 0 | H62: =SUM(D62+F62) -> 0 | I62: =SUM(H62*0.3025) -> 0 | K62: =SUM(J62*0.3025) -> 0 | L62: =SUM(H62+J62) -> 0 | M62: =SUM(L62*0.3025) -> 0
E63: =SUM(D63*0.3025) -> 0 | G63: =SUM(F63*0.3025) -> 0 | H63: =SUM(D63+F63) -> 0 | I63: =SUM(H63*0.3025) -> 0 | K63: =SUM(J63*0.3025) -> 0 | L63: =SUM(H63+J63) -> 0 | M63: =SUM(L63*0.3025) -> 0
E64: =SUM(D64*0.3025) -> 0 | G64: =SUM(F64*0.3025) -> 0 | H64: =SUM(D64+F64) -> 0 | I64: =SUM(H64*0.3025) -> 0 | K64: =SUM(J64*0.3025) -> 0 | L64: =SUM(H64+J64) -> 0 | M64: =SUM(L64*0.3025) -> 0
E65: =SUM(D65*0.3025) -> 0 | G65: =SUM(F65*0.3025) -> 0 | H65: =SUM(D65+F65) -> 0 | I65: =SUM(H65*0.3025) -> 0 | K65: =SUM(J65*0.3025) -> 0 | L65: =SUM(H65+J65) -> 0 | M65: =SUM(L65*0.3025) -> 0
A67: ■ 근린생활시설 분양면적표
A68: 평 | B68: 층별구분 | D68: 전용면적 | F68: 근린생활시설공용면적 | H68: 전체공용 | J68: 주차장면적 | L68: 계약면적 | N68: 비고 | Q68: 분양면적계 | R68: 과세면적 | S68: 비과세면적 | U68: 공사비 | V68: 부가세 | W68: 합계
A69: =B21 -> 201.0536 | B69: 1F | D69: 265.86 | E69: =D69*0.3025 -> 80.42265 | G69: =F69*0.3025 -> 0 | H69: =D69+F69 -> 265.86 | I69: =H69*0.3025 -> 80.42265 | K69: =J69*0.3025 -> 0 | L69: 664.64 | M69: =L69*0.3025 -> 201.0536 | P69: 과세 | Q69: =M69 -> 201.0536 | R69: =IF(P69="과세",Q69, 0) -> 201.0536 | S69: =Q69-R69 -> 0 | U69: =M69*사업수지표!$BC$33 -> 985162.64 | V69: =U69*10% -> 98516.264 | W69: =SUM(U69:V69) -> 1083678.9
A70: =B22 -> 193.8783 | B70: B1 | D70: 256.37 | E70: =D70*0.3025 -> 77.551925 | G70: =F70*0.3025 -> 0 | H70: =D70+F70 -> 256.37 | I70: =H70*0.3025 -> 77.551925 | K70: =J70*0.3025 -> 0 | L70: 640.92 | M70: =L70*0.3025 -> 193.8783 | Q70: =M70 -> 193.8783 | R70: =IF(P70="과세",Q70, 0) -> 0 | U70: =M70*사업수지표!$BC$33 -> 950003.67 | V70: =U70*10% -> 95000.367 | W70: =SUM(U70:V70) -> 1045004
Q71: =M71 -> 0 | R71: =IF(P71="과세",Q71, 0) -> 0 | U71: =M71*B71*사업수지표!$BC$33 -> 0 | V71: =U71*10% -> 0 | W71: =SUM(U71:V71) -> 0
Q72: =M72 -> 0 | R72: =IF(P72="과세",Q72, 0) -> 0 | U72: =M72*B72*사업수지표!$BC$33 -> 0 | V72: =U72*10% -> 0 | W72: =SUM(U72:V72) -> 0
A73: 소계 | D73: =SUM(D69:D72) -> 522.23 | E73: =SUM(D73*0.3025) -> 157.97457 | F73: =SUM(F69:F72) -> 0 | G73: =SUM(F73*0.3025) -> 0 | H73: =SUM(H69:H72) -> 522.23 | I73: =SUM(H73*0.3025) -> 157.97457 | J73: =SUM(J69:J72) -> 0 | K73: =SUM(J73*0.3025) -> 0 | L73: =SUM(L69:L72) -> 1305.56 | M73: =SUM(L73*0.3025) -> 394.9319 | Q73: =SUM(Q69:Q72) -> 394.9319 | R73: =SUM(R69:R72) -> 201.0536 | S73: =SUM(S69:S72) -> 0 | U73: =SUM(U69:U72) -> 1935166.3 | V73: =SUM(V69:V72) -> 193516.63 | W73: =SUM(W69:W72) -> 2128682.9
P75: 소계 | Q75: =SUM(Q59,Q73) -> 89880.44 | R75: =SUM(R59,R73) -> 201.0536 | S75: =SUM(S59,S73) -> 89485.508 | U75: 소계 | V75: =W59+W73 -> 4.4060767e+08

Sheet 사업수지표
A1: 경기도 화성시 장짐리 공동주택 신축사업 (Normal)
A3: 사 업 명 | G3: 경기도 화성시 장짐리 공동주택 신축사업
A4: 부지대표지번 | G4: 경기도 화성시 장짐리 228-1 일원
A5: 매입면적(토지) | G5: 105981 | M5: ㎡ | Z5: =G5*0.3025 -> 32059.252 | AI5: 평 | AJ5: 용적률 | AR5: 196.73 | AT5: % | AW5: 건폐율 | BA5: 14.55 | BK5: %
A6: 기부면적(도로등) | G6: 165 | M6: ㎡ | Z6: =G6*0.3025 -> 49.9125 | AI6: 평 | AJ6: 공사기간 | AR6: 37 | AT6: 개월 | AW6: 건축규모 | BB6: 지하 | BD6: 2 | BE6: 지상 | BG6: 24 | BI6: 20 | BK6: 동
A7: 유휴면적(토지) | G7: 0 | M7: ㎡ | Z7: =G7*0.3025 -> 0 | AI7: 평 | AJ7: 세대수 | AR7: 1885 | AT7: 세대 | AW7: equity | BA7: =AR89 -> 6585203
A8: 사업면적(토지) | G8: =G5-G6-G7 -> 105816 | M8: ㎡ | Z8: =G8*0.3025 -> 32009.34 | AI8: 평 | AJ8: 주차대수 | AR8: 2529 | AT8: 대 | AW8: 공사비선급금
A9: 전체연면적(건물) | G9: =SUM(G10,AR10) -> 297049.16 | M9: ㎡ | Z9: =G9*0.3025 -> 89857.371 | AI9: 평 | AJ9: 지하연면적(건물) | AR9: =AR10*0.3025 -> 26785.7 | AT9: 평 | AW9: 대여금
A10: 지상연면적(건물) | G10: 208501.39 | M10: ㎡ | Z10: =G10*0.3025 -> 63071.67 | AI10: 평 | AJ10: 지하연면적(건물) | AR10: 88547.77 | AT10: ㎡ | AW10: 신탁최대차입금 | BA10: =현금흐름표!BY129 -> 3082966.2 | BM10: (단위:천원) | CA10: 부가세미포함
A11: 구 분 | N11: 시행사 금액 | T11: 시공사 금액 | Z11: 금액 | AR11: 신탁 전 투입(vat포함) | AT11: 신탁후 | AU11: 분양불사업비 | AV11: 정산사업비 | AW11: 산출 내역 | BM11: 비 고 | BT11: 비율 | BW11: 발코니포함 | CA11: 발코니포함
N12: VAT별도 | T12: VAT별도 | Z12: 공급가액 | AF12: 부가세 | AL12: 총액 | AR12: Equity | AS12: PF | AT12: 계정대 | BM12: 분양가 | BS12: VAT포함
A13: 수입 | B13: 아파트 | G13: 타입 | I13: 59A | Z13: =AW13*BB13*BH13 -> 1.1894523e+08 | AF13: 0 | AL13: =Z13+AF13 -> 1.1894523e+08 | AW13: =분양개요!B6 -> 25.285975 | AZ13: 평 | BA13: × | BB13: =분양개요!D6 -> 14000 | BE13: 천원 | BG13: × | BH13: =분양개요!B50 -> 336 | BK13: 세대 | BM13: 세대당 | BP13: =Z13/BH13 -> 354003.65 | BR13: 천원 | BS13: 좌동 | BT13: =AL13/$AL$23 -> 0.12970004 | BW13: =BP13+$BB$22 -> 374003.65 | BY13: =BW13/AW13 -> 14790.952
G14: 타입 | I14: 84A | Z14: =AW14*BB14*BH14 -> 7.4908811e+08 | AF14: 0 | AL14: =Z14+AF14 -> 7.4908811e+08 | AW14: =분양개요!B7 -> 34.542475 | AZ14: 평 | BA14: × | BB14: =분양개요!D7 -> 14000 | BE14: 천원 | BG14: × | BH14: =분양개요!B51 -> 1549 | BK14: 세대 | BM14: 세대당 | BP14: =Z14/BH14 -> 483594.65 | BR14: 천원 | BS14: 좌동 | BT14: =AL14/$AL$23 -> 0.81681932 | BW14: =BP14+$BB$22 -> 503594.65 | BY14: =BW14/AW14 -> 14578.997
G15: 타입 | I15: 84B | Z15: =AW15*BB15*BH15 -> 0 | AF15: 0 | AL15: =Z15+AF15 -> 0 | AW15: =분양개요!B8 -> 0 | AZ15: 평 | BA15: × | BB15: =분양개요!D8 -> 0 | BE15: 천원 | BG15: × | BH15: =분양개요!B52 -> 0 | BK15: 세대 | BM15: 세대당 | BP15: =Z15/BH15 -> #DIV/0! | BR15: 천원 | BS15: 좌동 | BT15: =AL15/$AL$23 -> 0 | BW15: =BP15+$BB$22 -> #DIV/0! | BY15: =BW15/AW15 -> #DIV/0!
G16: 타입 | I16: 84C | Z16: =AW16*BB16*BH16 -> 0 | AF16: 0 | AL16: =Z16+AF16 -> 0 | AW16: =분양개요!B9 -> 0 | AZ16: 평 | BA16: × | BB16: =분양개요!D9 -> 0 | BE16: 천원 | BG16: × | BH16: =분양개요!B53 -> 0 | BK16: 세대 | BM16: 세대당 | BP16: =Z16/BH16 -> #DIV/0! | BR16: 천원 | BS16: 좌동 | BT16: =AL16/$AL$23 -> 0 | BW16: =BP16+$BB$22 -> #DIV/0! | BY16: =BW16/AW16 -> #DIV/0!
G17: 타입 | I17: 117A | Z17: =AW17*BB17*BH17 -> 0 | AF17: =분양개요!H36 -> 0 | AL17: =Z17+AF17 -> 0 | AW17: =분양개요!B10 -> 0 | AZ17: 평 | BA17: × | BB17: =분양개요!D10 -> 0 | BE17: 천원 | BG17: × | BH17: =분양개요!B54 -> 0 | BK17: 세대 | BM17: 세대당 | BP17: =Z17/BH17 -> #DIV/0! | BR17: 천원 | BS17: =AL17/BH17 -> #DIV/0! | BT17: =AL17/$AL$23 -> 0 | BW17: =BS17+BB22 -> #DIV/0! | BY17: =BW17/AW17 -> #DIV/0! | CA17: =BP17+BB22 -> #DIV/0! | CB17: =CA17/AW17 -> #DIV/0!
G18: 소계 | Z18: =SUM(Z13:AE17) -> 8.6803334e+08 | AF18: =SUM(AF13:AK17) -> 0 | AL18: =Z18+AF18 -> 8.6803334e+08 | AW18: =분양개요!I59 -> 62002.381 | AZ18: 평 | BA18: × | BB18: =Z18/AW18 -> 14000 | BE18: 천원 | BG18: | | BH18: =SUM(BH13:BJ17) -> 1885 | BK18: 세대 | BT18: =AL18/$AL$23 -> 0.94651937 | BV18: =Z18/$Z$23 -> 0.95109995
B19: 근생 | G19: 타입 | I19: 1층 | Z19: =AW19*BB19*BH19 -> 4021072 | AF19: 378594 | AL19: =Z19+AF19 -> 4399666 | AW19: =분양개요!B21 -> 201.0536 | AZ19: 평 | BA19: × | BB19: =분양개요!D21 -> 20000 | BE19: 천원 | BG19: × | BH19: 1 | BK19: 세대 | BM19: 세대당 | BP19: =Z19/BH19 -> 4021072 | BR19: 천원 | BS19: =AL19 -> 4399666 | BT19: =AL19/$AL$23 -> 0.004797476 | BV19: =Z19/$Z$23 -> 0.0044058692 | CA19: 부가세 과세
G20: 타입 | I20: 지하1층 | Z20: =AW20*BB20*BH20 -> 2908174.5 | AF20: 268144 | AL20: =Z20+AF20 -> 3176318.5 | AW20: =분양개요!B22 -> 193.8783 | AZ20: 평 | BA20: × | BB20: 15000 | BE20: 천원 | BG20: × | BH20: 1 | BK20: 세대 | BM20: 세대당 | BP20: =Z20/BH20 -> 2908174.5 | BR20: 천원 | BS20: =AL20 -> 3176318.5 | BT20: =AL20/$AL$23 -> 0.0034635156 | BV20: =Z20/$Z$23 -> 0.0031864728 | CA20: 공사성 | CB20: =분양개요!M32 -> 0.0022417361
G21: 소계 | Z21: =SUM(Z19:AE20) -> 6929246.5 | AF21: =SUM(AF19:AK20) -> 646738 | AL21: =SUM(AL19:AQ20) -> 7575984.5 | AW21: =분양개요!M73 -> 394.9319 | AZ21: 평 | BA21: × | BB21: =Z21/AW21 -> 17545.421 | BE21: 천원 | BG21: | | BH21: =SUM(BH19:BJ20) -> 2 | BK21: 세대 | BT21: =AL21/$AL$23 -> 0.0082609915 | BV21: =Z21/$Z$23 -> 0.007592342 | CA21: 사업성 | CB21: =CB20*CC21 -> 0.0017933889 | CC21: 0.8
B22: 발코니 확장비 | Z22: =BB22*BH22 -> 37700000 | AF22: =Z22*0.1 -> 3770000 | AL22: =SUM(Z22:AK22) -> 41470000 | BB22: 20000 | BE22: 천원/세대 | BG22: | | BH22: =BH18 -> 1885 | BK22: 세대 | BT22: =AL22/$AL$23 -> 0.045219643 | BV22: =Z22/$Z$23 -> 0.041307708 | CA22: 과세비율 | CC22: 부가세 | CD22: 면세분 | CE22: 과세분
B23: 매출합계 | N23: =#REF!+#REF!+#REF! -> #REF! | T23: =#REF!+#REF!+#REF! -> #REF! | Z23: =SUM(Z18,Z21,Z22) -> 9.1266259e+08 | AF23: =SUM(AF18,AF21,AF22) -> 4416738 | AL23: =SUM(AL18,AL21,AL22) -> 9.1707932e+08 | BT23: =SUM(BT18,BT21:BU22) -> 1 | BV23: =Z23/$Z$23 -> 1 | CA23: 1. 매출부가세 | CC23: =AF23 -> 4416738 | CD23: =CC23-CE23 -> 0 | CE23: =CC23 -> 4416738
A24: 비용 | B24: 토지비 | G24: 채권매입비용 | N24: 11500000 | T24: 11500000 | Z24: 96000000 | AF24: 0 | AL24: =Z24+AF24 -> 96000000 | AR24: 0 | AS24: 96000000 | AT24: =AL24-AR24-AS24 -> 0 | AU24: 0 | AV24: 0 | BM24: 군인공제회(매몰비용) | BT24: =AL24/$AL$23 -> 0.10468015 | BV24: =Z24/$Z$23 -> 0.10518674 | BY24: =G24 -> 채권매입비용 | CB24: =IF($CA24=$CA$21, $CB$21, IF($CA24=$CA$20,$CB$20, )) -> 0 | CC24: =AF24 -> 0 | CD24: =CC24-CE24 -> 0 | CE24: =CC24*CB24 -> 0
G25: 토지비(공동주택) | N25: 575000 | T25: =Z25 -> 13969158 | Z25: 13969158 | AL25: =Z25+AF25 -> 13969158 | AR25: 0 | AS25: =AL25 -> 13969158 | AT25: =AL25-AR25-AS25 -> 0 | AU25: 0 | AV25: 0 | BM25: 미매입부지(공동주택) | BT25: =AL25/$AL$23 -> 0.015232224 | BV25: =Z25/$Z$23 -> 0.015305939 | BY25: =G25 -> 토지비(공동주택) | CA25: 사업성 | CB25: =IF($CA25=$CA$21, $CB$21, IF($CA25=$CA$20,$CB$20, )) -> 0.0017933889 | CC25: =AF25 -> 0 | CD25: =CC25-CE25 -> 0 | CE25: =CC25*CB25 -> 0
G26: 토지비(기반시설부지) | Z26: 11960903 | AL26: =Z26+AF26 -> 11960903 | AR26: 0 | AS26: 11960903 | AT26: =AL26-AR26-AS26 -> 0 | AU26: 0 | AV26: 0 | BM26: 미매입부지(기반시설부지) | BT26: =AL26/$AL$23 -> 0.013042387 | BV26: =Z26/$Z$23 -> 0.013105504
G27: 토지비(211,222-2번지) | Z27: 7470960 | AL27: =Z27+AF27 -> 7470960 | AR27: 0 | AS27: =AL27 -> 7470960 | AT27: =AL27-AR27-AS27 -> 0 | AU27: 0 | AV27: 0 | BM27: 엠에스홀딩스 (7,470,960 토지매입비) | BT27: =AL27/$AL$23 -> 0.0081464709 | BV27: =Z27/$Z$23 -> 0.0081858949 | BW27: =AS27-5000000 -> 2470960
G28: 취등록세 | N28: 575000 | T28: =Z28 -> 1603249 | Z28: =AW28*BC28 -> 1603249 | AL28: =Z28+AF28 -> 1603249 | AR28: 0 | AS28: =(AS25+AS26+AS27)*BC28 -> 1603249 | AT28: 0 | AU28: 0 | AV28: 0 | AW28: =AS25+AS26+AS27 -> 33401021 | BA28: 천원 | BB28: × | BC28: 0.048 | BM28: 미매입부지(공동주택+기반시설부지+엠에스 토지) | BT28: =AL28/$AL$23 -> 0.0017482119 | BV28: =Z28/$Z$23 -> 0.0017566722 | BY28: =G28 -> 취등록세 | CA28: 사업성 | CB28: =IF($CA28=$CA$21, $CB$21, IF($CA28=$CA$20,$CB$20, )) -> 0.0017933889 | CC28: =AF28 -> 0 | CD28: =CC28-CE28 -> 0 | CE28: =CC28*CB28 -> 0
G29: 명도 및 보상비 | N29: 575000 | T29: =Z29 -> 3882030.6 | Z29: =AW29*BC29 -> 3882030.6 | AF29: 0 | AL29: =Z29+AF29 -> 3882030.6 | AR29: 0 | AS29: =AL29-AR29 -> 3882030.6 | AT29: =AL29-AR29-AS29 -> 0 | AU29: 0 | AV29: 0 | AW29: =Z24+Z25+Z26+Z27 -> 129401021 | BA29: 천원 | BB29: × | BC29: 0.03 | BT29: =AL29/$AL$23 -> 0.0042330369 | BV29: =Z29/$Z$23 -> 0.0042535223 | BY29: =G29 -> 명도 및 보상비 | CB29: =IF($CA29=$CA$21, $CB$21, IF($CA29=$CA$20,$CB$20, )) -> 0 | CC29: =AF29 -> 0 | CD29: =CC29-CE29 -> 0 | CE29: =CC29*CB29 -> 0
G30: 주식근질권해제비용 | Z30: 5000000 | AF30: 0 | AL30: =Z30+AF30 -> 5000000 | AR30: 0 | AS30: =AL30-AR30 -> 5000000 | BT30: =AL30/$AL$23 -> 0.0054520911 | BV30: =Z30/$Z$23 -> 0.0054784759
G31: 인허가 비용 | Z31: 5444723 | AF31: 0 | AL31: =Z31+AF31 -> 5444723 | AR31: 5444723 | AS31: =AL31-AR31 -> 0 | BM31: 농지보전부담금, 개발행위 이행보증금, 산지복구비 등 | BT31: =AL31/$AL$23 -> 0.0059370251 | BV31: =Z31/$Z$23 -> 0.0059657568
G32: 소계 | N32: =SUM(N24:S28) -> 12650000 | T32: =SUM(T24:Y28) -> 27072407 | Z32: =SUM(Z24:AE31) -> 1.4533102e+08 | AF32: =SUM(AF24:AK29) -> 0 | AL32: =SUM(AL24:AQ31) -> 1.4533102e+08 | AR32: =SUM(AR24:AR31) -> 5444723 | AS32: =SUM(AS24:AS31) -> 1.398863e+08 | AT32: =SUM(AT24:AT28) -> 0 | AU32: =SUM(AU24:AU31) -> 0 | AV32: =SUM(AV24:AV31) -> 0 | BT32: =AL32/$AL$23 -> 0.1584716 | BV32: =Z32/$Z$23 -> 0.1592385 | CC32: =SUM(CC24:CC28)=AF32 -> TRUE | CE32: =CC32*CB32 -> 0
B33: 건축비 | G33: 직접공사비(본공사) | N33: 94609110 | T33: =AW33*4200 -> 3.7740096e+08 | Z33: =AW33*BC33 -> 4.4030112e+08 | AF33: =Z33*분양개요!M32*0.1 -> 98703.89 | AL33: =Z33+AF33 -> 4.4039982e+08 | AT33: =AL33*90% -> 3.9635984e+08 | AV33: =AL33-AT33 -> 44039982 | AW33: =+Z9 -> 89857.371 | BA33: 평 | BB33: × | BC33: 4900 | BF33: 천원 | BM33: 서한 시공참여의향서 공사비 4,800천원(파일공사 제외,VAT제외) | BT33: =AL33/$AL$23 -> 0.48021999 | BV33: =Z33/$Z$23 -> 0.48243581 | BY33: =G33 -> 직접공사비(본공사) | CA33: 공사성 | CB33: =IF($CA33=$CA$21, $CB$21, IF($CA33=$CA$20,$CB$20, )) -> 0.0022417361 | CC33: =AF33 -> 98703.89 | CD33: =CC33-CE33 -> 98482.622 | CE33: =CC33*CB33 -> 221.26807
G34: 기타공사비(본공사) | BA34: 평 | BB34: × | BF34: 천원 | BT34: =AL34/$AL$23 -> 0 | BV34: =Z34/$Z$23 -> 0 | BY34: =G34 -> 기타공사비(본공사) | CA34: 공사성 | CB34: =IF($CA34=$CA$21, $CB$21, IF($CA34=$CA$20,$CB$20, )) -> 0.0022417361
G35: 각종인입비 | N35: 692261 | T35: =Z35 -> 2695721.1 | Z35: =AW35*BC35 -> 2695721.1 | AF35: =Z35*0.1 -> 269572.11 | AL35: =Z35+AF35 -> 2965293.2 | AT35: =AL35-AR35-AS35 -> 2965293.2 | AW35: =+Z9 -> 89857.371 | BA35: 평 | BB35: × | BC35: 30 | BF35: 천원 | BT35: =AL35/$AL$23 -> 0.0032334098 | BV35: =Z35/$Z$23 -> 0.0029536887 | BY35: =G35 -> 각종인입비 | CA35: 공사성 | CB35: =IF($CA35=$CA$21, $CB$21, IF($CA35=$CA$20,$CB$20, )) -> 0.0022417361 | CC35: =AF35 -> 269572.11 | CD35: =CC35-CE35 -> 268967.8 | CE35: =CC35*CB35 -> 604.30953
G36: 조건부이행공사비 | N36: 300000 | T36: 300000 | Z36: =AW36*BC36 -> 6401868 | AF36: =Z36*0.1 -> 640186.8 | AL36: =Z36+AF36 -> 7042054.8 | AT36: =AL36-AR36-AS36 -> 7042054.8 | AW36: =Z8 -> 32009.34 | BA36: 평 | BB36: × | BC36: 200 | BF36: 천원 | BT36: =AL36/$AL$23 -> 0.0076787848 | BV36: =Z36/$Z$23 -> 0.0070144959 | BY36: =G36 -> 조건부이행공사비 | CA36: 공사성 | CB36: =IF($CA36=$CA$21, $CB$21, IF($CA36=$CA$20,$CB$20, )) -> 0.0022417361 | CC36: =AF36 -> 640186.8 | CD36: =CC36-CE36 -> 638751.67 | CE36: =CC36*CB36 -> 1435.1298
G37: 예술장식품비 | N37: 300000 | T37: 300000 | Z37: =AW37*BC37*BI37 -> 685589.06 | AF37: =Z37*0.1 -> 68558.906 | AL37: =Z37+AF37 -> 754147.96 | AS37: 0 | AT37: =AL37-AR37-AS37 -> 754147.96 | AW37: =Z10 -> 63071.67 | BA37: 평 | BB37: × | BC37: 2174 | BF37: 천원 | BH37: × | BI37: 0.005 | BT37: =AL37/$AL$23 -> 0.00082233668 | BV37: =Z37/$Z$23 -> 0.00075119663 | BY37: =G37 -> 예술장식품비 | CA37: 공사성 | CB37: =IF($CA37=$CA$21, $CB$21, IF($CA37=$CA$20,$CB$20, )) -> 0.0022417361 | CC37: =AF37 -> 68558.906 | CD37: =CC37-CE37 -> 68405.215 | CE37: =CC37*CB37 -> 153.69097
G38: 소계 | N38: =SUM(N33:S36) -> 95601371 | T38: =SUM(T33:Y36) -> 3.8039668e+08 | Z38: =SUM(Z33:AE37) -> 4.500843e+08 | AF38: =SUM(AF33:AK37) -> 1077021.7 | AL38: =SUM(AL33:AQ37) -> 4.5116132e+08 | AR38: =SUM(AR33:AR37) -> 0 | AS38: =SUM(AS33:AS37) -> 0 | AT38: =SUM(AT33:AT37) -> 4.0712134e+08 | AU38: =SUM(AU33:AU37) -> 0 | AV38: =SUM(AV33:AV37) -> 44039982 | BT38: =AL38/$AL$23 -> 0.49195452 | BV38: =Z38/$Z$23 -> 0.4931552 | CC38: =SUM(CC33:CC37)=AF38 -> TRUE
B39: 용역비 | G39: 설계비 | N39: 1450000 | T39: 1450000 | Z39: 4368000 | AF39: =Z39*10% -> 436800 | AL39: =Z39+AF39 -> 4804800 | AR39: =AL39*10% -> 480480 | AS39: 0 | AT39: =AL39-AR39-AS39 -> 4324320 | AW39: =+Z9 -> 89857.371 | BA39: 평 | BB39: × | BC39: 80 | BF39: 천원 | BT39: =AL39/$AL$23 -> 0.0052392414 | BV39: =Z39/$Z$23 -> 0.0047859966 | BY39: =G39 -> 설계비 | CA39: 공사성 | CB39: =IF($CA39=$CA$21, $CB$21, IF($CA39=$CA$20,$CB$20, )) -> 0.0022417361 | CC39: =AF39 -> 436800 | CD39: =CC39-CE39 -> 435820.81 | CE39: =CC39*CB39 -> 979.19032
G40: 감리비 | N40: 2538293 | T40: =Z40 -> 9884310.8 | Z40: =AW40*BC40 -> 9884310.8 | AF40: =Z40*0.1 -> 988431.08 | AL40: =Z40+AF40 -> 10872742 | AS40: =현금흐름표!Y60 -> 0 | AT40: =AL40-AU40 -> 9785467.7 | AU40: =AL40*10% -> 1087274.2 | AW40: =+Z9 -> 89857.371 | BA40: 평 | BB40: × | BC40: 110 | BF40: 천원 | BT40: =AL40/$AL$23 -> 0.011855836 | BV40: =Z40/$Z$23 -> 0.010830192 | BY40: =G40 -> 감리비 | CA40: 공사성 | CB40: =IF($CA40=$CA$21, $CB$21, IF($CA40=$CA$20,$CB$20, )) -> 0.0022417361 | CC40: =AF40 -> 988431.08 | CD40: =CC40-CE40 -> 986215.28 | CE40: =CC40*CB40 -> 2215.8016
G41: 미매입 토지 용역비 | N41: 96941 | T41: =Z41 -> 0 | AS41: 0 | AT41: =AL41-AR41-AS41 -> 0 | BT41: =AL41/$AL$23 -> 0 | BV41: =Z41/$Z$23 -> 0 | BY41: =G41 -> 미매입 토지 용역비 | CA41: 공사성 | CB41: =IF($CA41=$CA$21, $CB$21, IF($CA41=$CA$20,$CB$20, )) -> 0.0022417361 | CC41: =AF41 -> 0 | CD41: =CC41-CE41 -> 0 | CE41: =CC41*CB41 -> 0
G42: 지구단위 용역비 | Z42: 1750000 | AF42: =Z42*10% -> 175000 | AL42: =Z42+AF42 -> 1925000 | AR42: 660000 | AS42: 0 | AT42: =AL42-AR42-AS42 -> 1265000 | BT42: =AL42/$AL$23 -> 0.0020990551 | BV42: =Z42/$Z$23 -> 0.0019174666 | BY42: =G42 -> 지구단위 용역비 | CA42: 사업성 | CB42: =IF($CA42=$CA$21, $CB$21, IF($CA42=$CA$20,$CB$20, )) -> 0.0017933889 | CC42: =AF42 -> 175000 | CD42: =CC42-CE42 -> 174686.16 | CE42: =CC42*CB42 -> 313.84305
G43: 소계 | N43: =SUM(N39:S41) -> 4085234 | T43: =SUM(T39:Y41) -> 11334311 | Z43: =SUM(Z39:AE42) -> 16002311 | AF43: =SUM(AF39:AK42) -> 1600231.1 | AL43: =SUM(AL39:AQ42) -> 17602542 | AR43: =SUM(AR39:AR42) -> 1140480 | AS43: =SUM(AS39:AS42) -> 0 | AT43: =SUM(AT39:AT42) -> 15374788 | BT43: =AL43/$AL$23 -> 0.019194132 | BV43: =Z43/$Z$23 -> 0.017533655 | CC43: =SUM(CC39:CC42)=AF43 -> TRUE
B44: 판매비 | G44: M/H부지임차비 | Z44: =AW44*BC44 -> 720000 | AF44: =Z44*0.1 -> 72000 | AL44: =Z44+AF44 -> 792000 | AR44: 0 | AS44: 0 | AT44: =AL44-AR44-AS44 -> 792000 | AW44: 24 | AZ44: 개월 | BB44: × | BC44: 30000 | BF44: 천원 | BT44: =AL44/$AL$23 -> 0.00086361123 | BV44: =Z44/$Z$23 -> 0.00078890053 | BY44: =G44 -> M/H부지임차비 | CA44: 사업성 | CB44: =IF($CA44=$CA$21, $CB$21, IF($CA44=$CA$20,$CB$20, )) -> 0.0017933889 | CC44: =AF44 -> 72000 | CD44: =CC44-CE44 -> 71870.876 | CE44: =CC44*CB44 -> 129.124
G45: M/H건립비 | Z45: =AW45*BC45 -> 1650000 | AF45: =Z45*0.1 -> 165000 | AL45: =Z45+AF45 -> 1815000 | AR45: 0 | AS45: 0 | AT45: =AL45*10% -> 181500 | AU45: =AL45-AT45 -> 1633500 | AW45: 300 | AZ45: 평 | BB45: × | BC45: 5500 | BF45: 천원 | BT45: =AL45/$AL$23 -> 0.0019791091 | BV45: =Z45/$Z$23 -> 0.0018078971 | BY45: =G45 -> M/H건립비 | CA45: 사업성 | CB45: =IF($CA45=$CA$21, $CB$21, IF($CA45=$CA$20,$CB$20, )) -> 0.0017933889 | CC45: =AF45 -> 165000 | CD45: =CC45-CE45 -> 164704.09 | CE45: =CC45*CB45 -> 295.90916
G46: M/H운영비 | Z46: =AW46*BC46 -> 630000 | AF46: =Z46*0.1 -> 63000 | AL46: =Z46+AF46 -> 693000 | AT46: =AL46/2 -> 346500 | AU46: =AL46-AT46 -> 346500 | AV46: . | AW46: 21 | AZ46: 개월 | BB46: × | BC46: 30000 | BF46: 천원 | BT46: =AL46/$AL$23 -> 0.00075565982 | BV46: =Z46/$Z$23 -> 0.00069028797 | BY46: =G46 -> M/H운영비 | CA46: 사업성 | CB46: =IF($CA46=$CA$21, $CB$21, IF($CA46=$CA$20,$CB$20, )) -> 0.0017933889 | CC46: =AF46 -> 63000 | CD46: =CC46-CE46 -> 62887.017 | CE46: =CC46*CB46 -> 112.9835
G47: 광고홍보비 | Z47: =AW47*BC47 -> 9126625.9 | AF47: =Z47*0.1 -> 912662.59 | AL47: =Z47+AF47 -> 10039288 | AR47: 0 | AS47: 0 | AT47: =AL47/2 -> 5019644.2 | AU47: =AL47/2 -> 5019644.2 | AW47: =Z23 -> 9.1266259e+08 | AZ47: 천원 | BB47: × | BC47: 0.01 | BT47: =AL47/$AL$23 -> 0.010947023 | BV47: =Z47/$Z$23 -> 0.01 | BY47: =G47 -> 광고홍보비 | CA47: 사업성 | CB47: =IF($CA47=$CA$21, $CB$21, IF($CA47=$CA$20,$CB$20, )) -> 0.0017933889 | CC47: =AF47 -> 912662.59 | CD47: =CC47-CE47 -> 911025.83 | CE47: =CC47*CB47 -> 1636.7589
G48: 분양보증 수수료 | Z48: =AW48*BC48*BI48/12 -> 3747010.6 | AF48: 0 | AL48: =Z48+AF48 -> 3747010.6 | AS48: 0 | AT48: =AL48-AR48-AS48 -> 3747010.6 | AW48: =Z18*70% -> 6.0762334e+08 | AZ48: 천원 | BB48: × | BC48: 37 | BF48: 개월 | BH48: × | BI48: 0.002 | BT48: =AL48/$AL$23 -> 0.0040858086 | BV48: =Z48/$Z$23 -> 0.0041055814 | BY48: =G48 -> 분양보증 수수료 | CA48: 사업성 | CB48: =IF($CA48=$CA$21, $CB$21, IF($CA48=$CA$20,$CB$20, )) -> 0.0017933889 | CC48: =AF48 -> 0 | CD48: =CC48-CE48 -> 0 | CE48: =CC48*CB48 -> 0
G49: 분양수수료(공동주택) | Z49: =AW49*BC49 -> 9425000 | AF49: =Z49*0.1 -> 942500 | AL49: =Z49+AF49 -> 10367500 | AS49: =현금흐름표!X70+현금흐름표!Y70 -> 0 | AT49: =AL49 -> 10367500 | AW49: =AR7 -> 1885 | AZ49: 세대 | BB49: × | BC49: 5000 | BF49: 천원 | BT49: =AL49/$AL$23 -> 0.011304911 | BV49: =Z49/$Z$23 -> 0.010326927 | BY49: =G49 -> 분양수수료(공동주택) | CA49: 사업성 | CB49: =IF($CA49=$CA$21, $CB$21, IF($CA49=$CA$20,$CB$20, )) -> 0.0017933889 | CC49: =AF49 -> 942500 | CD49: =CC49-CE49 -> 940809.73 | CE49: =CC49*CB49 -> 1690.269
G50: 분양수수료(근생) | Z50: =AW50*BC50 -> 554339.72 | AF50: =Z50*0.1 -> 55433.972 | AL50: =Z50+AF50 -> 609773.69 | AS50: =현금흐름표!X71+현금흐름표!Y71 -> 0 | AT50: =AL50 -> 609773.69 | AW50: =Z21 -> 6929246.5 | AZ50: 천원 | BB50: × | BC50: 0.08 | BT50: =AL50/$AL$23 -> 0.00066490834 | BV50: =Z50/$Z$23 -> 0.00060738736 | BY50: =G50 -> 분양수수료(근생) | CA50: 사업성 | CB50: =IF($CA50=$CA$21, $CB$21, IF($CA50=$CA$20,$CB$20, )) -> 0.0017933889 | CC50: =AF50 -> 55433.972 | CD50: =CC50-CE50 -> 55334.557 | CE50: =CC50*CB50 -> 99.414668
G51: 분양촉진비 | Z51: =AW51*BC51 -> 5655000 | AF51: =Z51*0.1 -> 565500 | AL51: =Z51+AF51 -> 6220500 | AT51: =AL51/2 -> 3110250 | AV51: =AL51/2 -> 3110250 | AW51: =AR7 -> 1885 | AZ51: 세대 | BB51: × | BC51: 3000 | BF51: 천원 | BT51: =AL51/$AL$23 -> 0.0067829465 | BV51: =Z51/$Z$23 -> 0.0061961563 | BY51: =G51 -> 분양촉진비 | CA51: 사업성 | CB51: =IF($CA51=$CA$21, $CB$21, IF($CA51=$CA$20,$CB$20, )) -> 0.0017933889 | CC51: =AF51 -> 565500 | CD51: =CC51-CE51 -> 564485.84 | CE51: =CC51*CB51 -> 1014.1614
G52: 소계 | N52: =SUM(N44:S50) -> 0 | T52: =SUM(T44:Y50) -> 0 | Z52: =SUM(Z44:AE51) -> 31507976 | AF52: =SUM(AF44:AK51) -> 2776096.6 | AL52: =SUM(AL44:AQ51) -> 34284073 | AR52: =SUM(AR44:AR51) -> 0 | AS52: =SUM(AS44:AS51) -> 0 | AT52: =SUM(AT44:AT51) -> 24174178 | AU52: =SUM(AU44:AU51) -> 6999644.2 | AV52: =SUM(AV44:AV51) -> 3110250 | BT52: =AL52/$AL$23 -> 0.037383977 | BV52: =Z52/$Z$23 -> 0.034523138 | CC52: =SUM(CC44:CC51)=AF52 -> TRUE
B53: 부대비 | G53: 신탁보수 | N53: 500000 | T53: =N53 -> 500000 | Z53: =AW53*BC53 -> 27379878 | AL53: =Z53+AF53 -> 27379878 | AS53: =AL53*10% -> 2737987.8 | AT53: =AL53-AR53-AS53 -> 24641890 | AW53: =Z23 -> 9.1266259e+08 | AZ53: 천원 | BB53: × | BC53: 0.03 | BT53: =AL53/$AL$23 -> 0.029855517 | BV53: =Z53/$Z$23 -> 0.03 | BY53: =G53 -> 신탁보수 | CB53: =IF($CA53=$CA$21, $CB$21, IF($CA53=$CA$20,$CB$20, )) -> 0 | CC53: =AF53 -> 0 | CD53: =CC53-CE53 -> 0 | CE53: =CC53*CB53 -> 0
AL54: =Z54+AF54 -> 0 | AS54: =AL54 -> 0 | BT54: =AL54/$AL$23 -> 0 | BV54: =Z54/$Z$23 -> 0 | BY54: =G54 -> 0 | CB54: =IF($CA54=$CA$21, $CB$21, IF($CA54=$CA$20,$CB$20, )) -> 0 | CC54: =AF54 -> 0 | CD54: =CC54-CE54 -> 0 | CE54: =CC54*CB54 -> 0
G55: 시행사운영비 | N55: 1500000 | T55: =Z55 -> 1850000 | Z55: =AW55*BC55 -> 1850000 | AL55: =Z55+AF55 -> 1850000 | AS55: 0 | AT55: =AL55/2 -> 925000 | AU55: =AL55/2 -> 925000 | AW55: 50000 | AZ55: 천원 | BB55: × | BC55: 37 | BE55: 개월 | BT55: =AL55/$AL$23 -> 0.0020172737 | BV55: =Z55/$Z$23 -> 0.0020270361 | BY55: =G55 -> 시행사운영비 | CA55: 사업성 | CB55: =IF($CA55=$CA$21, $CB$21, IF($CA55=$CA$20,$CB$20, )) -> 0.0017933889 | CC55: =AF55 -> 0 | CD55: =CC55-CE55 -> 0 | CE55: =CC55*CB55 -> 0
AL56: =Z56+AF56 -> 0 | AT56: =AL56-AR56-AS56 -> 0 | BT56: =AL55/$AL$23 -> 0.0020172737 | BV56: =Z56/$Z$23 -> 0 | BY56: =G56 -> 0 | CB56: =IF($CA56=$CA$21, $CB$21, IF($CA56=$CA$20,$CB$20, )) -> 0 | CC56: =AF56 -> 0 | CD56: =CC56-CE56 -> 0 | CE56: =CC56*CB56 -> 0
G57: 입주관리비 | Z57: =AW57*BC57 -> 565500 | AF57: =Z57*0.1 -> 56550 | AL57: =Z57+AF57 -> 622050 | AT57: 0 | AU57: =AL57 -> 622050 | AW57: 1885 | AZ57: 세대 | BB57: × | BC57: 300 | BF57: 천원 | BT57: =AL57/$AL$23 -> 0.00067829465 | BV57: =Z57/$Z$23 -> 0.00061961563 | BY57: =G57 -> 입주관리비 | CA57: 사업성 | CB57: =IF($CA57=$CA$21, $CB$21, IF($CA57=$CA$20,$CB$20, )) -> 0.0017933889 | CC57: =AF57 -> 56550 | CD57: =CC57-CE57 -> 56448.584 | CE57: =CC57*CB57 -> 101.41614
G58: 예비비 | N58: 2000000 | T58: 2000000 | Z58: =AW58*BC58 -> 9126625.9 | AL58: =Z58+AF58 -> 9126625.9 | AT58: =AL58/2 -> 4563312.9 | AU58: =AL58/2 -> 4563312.9 | AW58: =Z23 -> 9.1266259e+08 | BB58: × | BC58: 0.01 | BT58: =AL58/$AL$23 -> 0.0099518391 | BV58: =Z58/$Z$23 -> 0.01 | BY58: =G58 -> 예비비 | CB58: =IF($CA58=$CA$21, $CB$21, IF($CA58=$CA$20,$CB$20, )) -> 0 | CC58: =AF58 -> 0 | CD58: =CC58-CE58 -> 0 | CE58: =CC58*CB58 -> 0
G59: 소계 | N59: =SUM(N53:S55) -> 2000000 | T59: =SUM(T53:Y55) -> 2350000 | Z59: =SUM(Z53:AE58) -> 38922003 | AF59: =SUM(AF53:AK58) -> 56550 | AL59: =SUM(AL53:AQ58) -> 38978553 | AR59: =SUM(AR53:AR58) -> 0 | AS59: =SUM(AS53:AS58) -> 2737987.8 | AT59: =SUM(AT53:AT58) -> 30130203 | AU59: =SUM(AU53:AU58) -> 6110362.9 | AV59: =SUM(AV53:AV58) -> 0 | BT59: =AL59/$AL$23 -> 0.042502925 | BV59: =Z59/$Z$23 -> 0.042646652 | CC59: =SUM(CC53:CC58)=AF59 -> TRUE
B60: 제세 공과금 | G60: 보존등기비 | N60: 3215913 | T60: =(T33+T39+T40+T36+#REF!)*BC60 -> #REF! | Z60: =AW60*BC60 -> 14896033 | AF60: 0 | AL60: =Z60+AF60 -> 14896033 | AT60: =AL60-AR60-AS60 -> 14896033 | AW60: =Z33+Z39+Z40+Z35+Z36+Z55 -> 4.6550102e+08 | BB60: × | BC60: 0.032 | BT60: =AL60/$AL$23 -> 0.016242905 | BV60: =Z60/$Z$23 -> 0.016321511 | BY60: =G60 -> 보존등기비 | CB60: =IF($CA60=$CA$21, $CB$21, IF($CA60=$CA$20,$CB$20, )) -> 0 | CC60: =AF60 -> 0 | CD60: =CC60-CE60 -> 0 | CE60: =CC60*CB60 -> 0
G61: 상하수도분담금 | N61: 1670000 | T61: =Z61 -> 1508000 | Z61: =AW61*BC61 -> 1508000 | AF61: 0 | AL61: =Z61+AF61 -> 1508000 | AS61: 0 | AT61: =AL61-AR61-AS61 -> 1508000 | AW61: 1885 | AZ61: 세대 | BB61: × | BC61: 800 | BF61: 천원 | BT61: =AL61/$AL$23 -> 0.0016443507 | BV61: =Z61/$Z$23 -> 0.0016523083 | BY61: =G61 -> 상하수도분담금 | CB61: =IF($CA61=$CA$21, $CB$21, IF($CA61=$CA$20,$CB$20, )) -> 0 | CC61: =AF61 -> 0 | CD61: =CC61-CE61 -> 0 | CE61: =CC61*CB61 -> 0
G62: 토지분재산세 | Z62: =AW62*BC62*BI62 -> 548685.27 | AF62: 0 | AL62: =Z62+AF62 -> 548685.27 | AT62: =AL62-AR62-AS62 -> 548685.27 | AW62: =Z24+Z25+Z26 -> 121930061 | AZ62: 천원 | BB62: × | BC62: 1.5 | BH62: × | BI62: 0.003 | BT62: =AL62/$AL$23 -> 0.00059829642 | BV62: =Z62/$Z$23 -> 0.00060119181 | BY62: =G62 -> 토지분재산세 | CB62: =IF($CA62=$CA$21, $CB$21, IF($CA62=$CA$20,$CB$20, )) -> 0 | CC62: =AF62 -> 0 | CD62: =CC62-CE62 -> 0 | CE62: =CC62*CB62 -> 0
G63: 학교용지부담금 | Z63: =AW63*BC63 -> 3472133.4 | AF63: 0 | AL63: =Z63+AF63 -> 3472133.4 | AT63: =AL63-AR63-AS63 -> 3472133.4 | AW63: =Z18 -> 8.6803334e+08 | AZ63: 천원 | BB63: × | BC63: 0.004 | BT63: =AL63/$AL$23 -> 0.0037860775 | BV63: =Z63/$Z$23 -> 0.0038043998 | BY63: =G63 -> 학교용지부담금 | CB63: =IF($CA63=$CA$21, $CB$21, IF($CA63=$CA$20,$CB$20, )) -> 0 | CC63: =AF63 -> 0
G64: 지방교육세 | Z64: =AW64*BC64 -> 109737.05 | AF64: 0 | AL64: =Z64+AF64 -> 109737.05 | AT64: =AL64-AR64-AS64 -> 109737.05 | AW64: =Z62 -> 548685.27 | BB64: × | BC64: 0.2 | BT64: =AL64/$AL$23 -> 0.00011965928 | BV64: =Z64/$Z$23 -> 0.00012023836
G65: 도시계획세 | N65: 1670001 | T65: =Z65 -> 121930.06 | Z65: =AW65*BC65*BI65 -> 121930.06 | AF65: 0 | AL65: =Z65+AF65 -> 121930.06 | AT65: =AL65-AR65-AS65 -> 121930.06 | AW65: =Z24+Z25+Z26 -> 121930061 | AZ65: 천원 | BB65: × | BC65: 0.5 | BH65: × | BI65: 0.002 | BT65: =AL65/$AL$23 -> 0.00013295476 | BV65: =Z65/$Z$23 -> 0.00013359818 | BY65: =G65 -> 도시계획세 | CB65: =IF($CA65=$CA$21, $CB$21, IF($CA65=$CA$20,$CB$20, )) -> 0 | CC65: =AF65 -> 0 | CD65: =CC65-CE65 -> 0 | CE65: =CC65*CB65 -> 0
G66: 소계 | N66: =SUM(N60:S62) -> 4885913 | T66: =SUM(T60:Y62) -> #REF! | Z66: =SUM(Z60:AE65) -> 20656518 | AF66: =SUM(AF60:AK65) -> 0 | AL66: =SUM(AL60:AQ65) -> 20656518 | AR66: =SUM(AR60:AR65) -> 0 | AS66: =SUM(AS60:AS65) -> 0 | AT66: =SUM(AT60:AT65) -> 20656518 | AU66: =SUM(AU60:AU65) -> 0 | AV66: =SUM(AV60:AV65) -> 0 | BT66: =AL66/$AL$23 -> 0.022524244 | BV66: =Z66/$Z$23 -> 0.022633248 | CC66: =SUM(CC60:CC65)=SUM(AF60:AK65) -> TRUE
BV67: =Z67/$Z$23 -> 0 | BY67: =G67 -> 0 | CB67: =IF($CA67=$CA$21, $CB$21, IF($CA67=$CA$20,$CB$20, )) -> 0 | CC67: =AF67 -> 0 | CD67: =CC67-CE67 -> 0 | CE67: =CC67*CB67 -> 0
BV68: =Z68/$Z$23 -> 0 | BY68: =G68 -> 0 | CB68: =IF($CA68=$CA$21, $CB$21, IF($CA68=$CA$20,$CB$20, )) -> 0 | CC68: =AF68 -> 0 | CD68: =CC68-CE68 -> 0 | CE68: =CC68*CB68 -> 0
BV69: =Z69/$Z$23 -> 0 | BY69: =G69 -> 0 | CB69: =IF($CA69=$CA$21, $CB$21, IF($CA69=$CA$20,$CB$20, )) -> 0
BV70: =Z70/$Z$23 -> 0 | BY70: =G70 -> 0 | CB70: =IF($CA70=$CA$21, $CB$21, IF($CA70=$CA$20,$CB$20, )) -> 0 | CC70: =AF70 -> 0 | CD70: =CC70-CE70 -> 0 | CE70: =CC70*CB70 -> 0
G71: 소계 | N71: =SUM(N67) -> 0 | T71: =SUM(T67) -> 0 | Z71: =SUM(Z67:AE70) -> 0 | AF71: =SUM(AF67:AK70) -> 0 | AL71: =SUM(AL67:AQ70) -> 0 | AR71: =SUM(AR67:AR70) -> 0 | AS71: =SUM(AS67:AS70) -> 0 | AT71: =SUM(AT67:AT70) -> 0 | BT71: =AL71/$AL$23 -> 0 | BV71: =Z71/$Z$23 -> 0 | BY71: =G71 -> 소계 | CB71: =IF($CA71=$CA$21, $CB$21, IF($CA71=$CA$20,$CB$20, )) -> 0 | CC71: =SUM(CC67:CC70)=AF71 -> TRUE
B72: 금융비 | BV72: =Z72/$Z$23 -> 0 | BY72: =G72 -> 0 | CB72: =IF($CA72=$CA$21, $CB$21, IF($CA72=$CA$20,$CB$20, )) -> 0 | CE72: =CC72*CB72 -> 0
BV73: =Z73/$Z$23 -> 0 | BY73: =G73 -> 0 | CB73: =IF($CA73=$CA$21, $CB$21, IF($CA73=$CA$20,$CB$20, )) -> 0 | CE73: =CC73*CB73 -> 0
BV74: =Z74/$Z$23 -> 0 | BY74: =G74 -> 0 | CB74: =IF($CA74=$CA$21, $CB$21, IF($CA74=$CA$20,$CB$20, )) -> 0 | CE74: =CC74*CB74 -> 0
G75: 신탁대지급금이자 | N75: =현금흐름표!#REF! -> #REF! | T75: =현금흐름표!#REF! -> #REF! | Z75: =현금흐름표!N88 -> 28436.963 | AF75: 0 | AL75: =Z75+AF75 -> 28436.963 | AT75: =AL75-AR75-AS75 -> 28436.963 | AW75: 신탁계정대 금리 | BC75: : | BD75: 0.0777 | BT75: =AL75/$AL$23 -> 3.1008182e-05 | BV75: =Z75/$Z$23 -> 3.1158243e-05 | BY75: =G75 -> 신탁대지급금이자 | CB75: =IF($CA75=$CA$21, $CB$21, IF($CA75=$CA$20,$CB$20, )) -> 0 | CC75: =AF75 -> 0 | CD75: =CC75-CE75 -> 0 | CE75: =CC75*CB75 -> 0
G76: 중도금대출이자 | Z76: =현금흐름표!BY143 -> 21495221 | AF76: 0 | AL76: =Z76+AF76 -> 21495221 | AT76: 0 | AU76: =AL76 -> 21495221 | AW76: 중도금이자 금리 | BC76: : | BD76: 0.042 | BT76: =AL76/$AL$23 -> 0.023438781 | BV76: =Z76/$Z$23 -> 0.02355221 | BY76: =G76 -> 중도금대출이자 | CB76: =IF($CA76=$CA$21, $CB$21, IF($CA76=$CA$20,$CB$20, )) -> 0 | CC76: =AF76 -> 0 | CD76: =CC76-CE76 -> 0 | CE76: =CC76*CB76 -> 0
G77: 중도금주선수수료 | Z77: =ROUNDDOWN(AW77*BD77,-3) -> 785000 | AF77: =Z77*0.1 -> 78500 | AL77: =Z77+AF77 -> 863500 | AU77: =AL77 -> 863500 | AW77: =현금흐름표!BY141 -> 5.238504e+08 | BA77: 천원 | BC77: × | BD77: 0.0015 | BT77: =AL77/$AL$23 -> 0.00094157613 | BV77: =Z77/$Z$23 -> 0.00086012072
G78: PF부대비용 | Z78: 450000 | AF78: =Z78*10% -> 45000 | AL78: =Z78+AF78 -> 495000 | AS78: =AL78-AR78 -> 495000 | AT78: 0 | BT78: =AL78/$AL$23 -> 0.00053975702 | BV78: =Z78/$Z$23 -> 0.00049306283 | BY78: =G78 -> PF부대비용 | CA78: 사업성 | CB78: =IF($CA78=$CA$21, $CB$21, IF($CA78=$CA$20,$CB$20, )) -> 0.0017933889 | CC78: =AF78 -> 45000 | CD78: =CC78-CE78 -> 44919.298 | CE78: =CC78*CB78 -> 80.702499
G79: 금융자문수수료 | N79: 3555661 | T79: =Z79 -> 4500000 | Z79: 4500000 | AF79: =Z79*0.1 -> 450000 | AL79: =Z79+AF79 -> 4950000 | AS79: =AL79 -> 4950000 | AT79: =AL79-AR79-AS79 -> 0 | AW79: 일식 | BT79: =AL79/$AL$23 -> 0.0053975702 | BV79: =Z79/$Z$23 -> 0.0049306283 | BY79: =G79 -> 금융자문수수료 | CA79: 사업성 | CB79: =IF($CA79=$CA$21, $CB$21, IF($CA79=$CA$20,$CB$20, )) -> 0.0017933889 | CC79: =AF79 -> 450000 | CD79: =CC79-CE79 -> 449192.98 | CE79: =CC79*CB79 -> 807.02499
G80: PF취급수수료 | N80: 3555662 | T80: =Z80 -> 0 | AF80: 0 | AL80: =Z80+AF80 -> 0 | AS80: =AL80 -> 0 | AT80: =AL80-AR80-AS80 -> 0 | BA80: 천원 | BC80: × | BD80: 0 | BM80: IRR | BS80: 0.11 | BT80: =AL80/$AL$23 -> 0 | BV80: =Z80/$Z$23 -> 0 | BY80: =G80 -> PF취급수수료 | CA80: 사업성 | CB80: =IF($CA80=$CA$21, $CB$21, IF($CA80=$CA$20,$CB$20, )) -> 0.0017933889 | CC80: =AF80 -> 0 | CD80: =CC80-CE80 -> 0 | CE80: =CC80*CB80 -> 0
G81: PF이자 | J81: 일시 | N81: 3555660 | T81: =Z81 -> 89918693 | Z81: =현금흐름표!N94 -> 89918693 | AF81: 0 | AL81: =Z81+AF81 -> 89918693 | AS81: 0 | AT81: 0 | AV81: =AL81 -> 89918693 | AW81: =ROUNDUP(현금흐름표!N109,-6) -> 149000000 | BA81: 천원 | BC81: × | BD81: ='IRR 계산'!C2 -> 0.11 | BG81: IRR 11% | BM81: 토지비+초기금융비용 : | BS81: =AS89 -> 1.4806929e+08 | BT81: =AL81/$AL$23 -> 0.098048981 | BV81: =Z81/$Z$23 -> 0.098523479 | BY81: =J81 -> 일시 | CB81: =IF($CA81=$CA$21, $CB$21, IF($CA81=$CA$20,$CB$20, )) -> 0 | CC81: =AF81 -> 0 | CD81: =CC81-CE81 -> 0 | CE81: =CC81*CB81 -> 0
J82: 한도 | Z82: =현금흐름표!N95 -> 0 | AF82: 0 | AL82: =Z82+AF82 -> 0 | AS82: 0 | AT82: =AL82-AR82-AS82 -> 0 | BA82: 천원 | BC82: × | BD82: =BD81 -> 0.11 | BM82: 대출기간 50개월 : 10M+37M+3M | BT82: =AL82/$AL$23 -> 0 | BV82: =Z82/$Z$23 -> 0 | BY82: =J82 -> 한도 | CB82: =IF($CA82=$CA$21, $CB$21, IF($CA82=$CA$20,$CB$20, )) -> 0 | CC82: =AF82 -> 0 | CD82: =CC82-CE82 -> 0 | CE82: =CC82*CB82 -> 0
BV83: =Z83/$Z$23 -> 0 | BY83: =G83 -> 0 | CA83: 사업성 | CB83: =IF($CA83=$CA$21, $CB$21, IF($CA83=$CA$20,$CB$20, )) -> 0.0017933889 | CC83: =AF83 -> 0 | CD83: =CC83-CE83 -> 0 | CE83: =CC83*CB83 -> 0
BV84: =Z84/$Z$23 -> 0 | BY84: =G84 -> 0 | CB84: =IF($CA84=$CA$21, $CB$21, IF($CA84=$CA$20,$CB$20, )) -> 0 | CC84: =AF84 -> 0 | CD84: =CC84-CE84 -> 0 | CE84: =CC84*CB84 -> 0
BV85: =Z85/$Z$23 -> 0 | BY85: =G85 -> 0 | CA85: 사업성 | CB85: =IF($CA85=$CA$21, $CB$21, IF($CA85=$CA$20,$CB$20, )) -> 0.0017933889 | CC85: =AF85 -> 0 | CD85: =CC85-CE85 -> 0 | CE85: =CC85*CB85 -> 0
BV86: =Z86/$Z$23 -> 0 | BY86: =G86 -> 0 | CA86: 사업성 | CB86: =IF($CA86=$CA$21, $CB$21, IF($CA86=$CA$20,$CB$20, )) -> 0.0017933889 | CC86: =AF86 -> 0 | CD86: =CC86-CE86 -> 0 | CE86: =CC86*CB86 -> 0
G87: 소계 | N87: =SUM(N72:S78) -> #REF! | T87: =SUM(T72:Y78) -> #REF! | Z87: =SUM(Z75:AE86) -> 1.1717735e+08 | AF87: =SUM(AF75:AK86) -> 573500 | AL87: =SUM(AL75:AQ86) -> 1.1775085e+08 | AR87: =SUM(AR75:AR86) -> 0 | AS87: =SUM(AS75:AS86) -> 5445000 | AT87: =SUM(AT75:AT86) -> 28436.963 | AU87: =SUM(AU75:AU86) -> 22358721 | AV87: =SUM(AV75:AV86) -> 89918693 | BT87: =AL87/$AL$23 -> 0.12839767 | BV87: =Z87/$Z$23 -> 0.12839066 | CC87: =SUM(CC75:CC86)=AF87 -> FALSE
B88: 납부부가세 | Z88: =CD89 -> -5993008.3 | AF88: =CC89 -> -1588161.3 | AL88: =CE89 -> -7581169.7 | AT88: =AL88 -> -7581169.7 | BT88: =AL88/$AL$23 -> -0.0082666455 | BV88: =Z88/$Z$23 -> -0.0065665104 | CA88: 2. 매입부가세 | CC88: =SUM(CC24:CC87) -> 6004899.3 | CD88: =SUM(CD24:CD87) -> 5993008.3 | CE88: =SUM(CE24:CE87) -> 11890.998
B89: 지 출 합 계 | N89: =N87+N71+N66+N59+N52+N43+N38+N32 -> #REF! | T89: =T87+T71+T66+T59+T52+T43+T38+T32 -> #REF! | Z89: =Z87+Z71+Z66+Z59+Z52+Z43+Z38+Z32+Z88 -> 8.1368847e+08 | AF89: =AF87+AF71+AF66+AF59+AF52+AF43+AF38+AF32+AF88 -> 4495238 | AL89: =AL87+AL71+AL66+AL59+AL52+AL43+AL38+AL32+AL88 -> 8.1818371e+08 | AR89: =AR32+AR38+AR43+AR52+AR59+AR66+AR71+AR87+AR88 -> 6585203 | AS89: =AS88+AS87+AS66+AS59+AS52+AS43+AS38+AS32 -> 1.4806929e+08 | AT89: =AT32+AT38+AT43+AT59+AT66+AT71+AT87+AT52+AT88 -> 4.8990429e+08 | AU89: =AU32+AU38+AU43+AU59+AU66+AU71+AU87+AU52+AU88 -> 35468728 | AV89: =AV32+AV38+AV43+AV59+AV66+AV71+AV87+AV52+AV88 -> 1.3706893e+08 | BV89: =Z89/$Z$23 -> 0.89155454 | CA89: 납부부가세 | CC89: =CC23-CC88 -> -1588161.3 | CD89: =CD23-CD88 -> -5993008.3 | CE89: =CC89+CD89 -> -7581169.7
A90: 매출이익(수입-비용) | N90: =N23-N89 -> #REF! | T90: =T23-T89 -> #REF! | Z90: =Z23-Z89 -> 98974115 | AF90: =AF23-AF89 -> -78500 | AL90: =AL23-AL89 -> 98895615 | AR90: 수익률 | AS90: =Z90/Z23 -> 0.10844546 | BV90: =Z90/$Z$23 -> 0.10844546
AQ91: VAT포함 수익률 | AS91: =AL90/AL23 -> 0.10783758 | AT91: =149000000 -> 149000000
B92: 분양대금 | H92: 사업이익 | Z92: Equity | AF92: 시공사유보(10%) | AR92: BEP | AT92: =AT91-AS89 -> 930711.6
B93: =AL23 -> 9.1707932e+08 | H93: =Z90 -> 98974115 | Z93: =현금흐름표!N105 -> 6585203 | AF93: =Z33*10% -> 44030112 | AR93: =(B93-H93-Z93-AF93-AL93)/B93 -> 0.83688496 | AS93: =Z93/Z23 -> 0.0072153752 | AT93: =AS93+AS90 -> 0.11566084

Sheet 현금흐름표
A1: ● 자금계획 (Cash Flow) 안 | N1: PF대출기간 | AB1: 1 | AC1: 2 | AD1: 3 | AE1: 4 | AF1: 5 | AG1: 6 | AH1: 7 | AI1: 8 | AJ1: 9 | AK1: 10 | AL1: 11 | AM1: 12 | AN1: 13 | AO1: 14 | AP1: 15 | AQ1: 16 | AR1: 17 | AS1: 18 | AT1: 19 | AU1: 20 | AV1: 21 | AW1: 22 | AX1: 23 | AY1: 24 | AZ1: 25 | BA1: 26 | BB1: 27 | BC1: 28 | BD1: 29 | BE1: 30 | BF1: 31 | BG1: 32 | BH1: 33 | BI1: 34 | BJ1: 35 | BK1: 36 | BL1: 37 | BM1: 38 | BN1: 39 | CC1: 3 | CD1: 4 | CE1: 5 | CF1: 6 | CG1: 7 | CH1: 8 | CI1: 9 | CJ1: 10 | CK1: 11 | CL1: 12 | CM1: 13 | CN1: 14 | CO1: 15 | CP1: 16 | CQ1: 17 | CR1: 18 | CS1: 19 | CT1: 20 | CU1: 21 | CV1: 22 | CW1: 23 | CX1: 24 | CY1: 25 | CZ1: 26 | DA1: 27 | DB1: 28 | DC1: 29 | DD1: 30 | DE1: 31 | DF1: 32 | DG1: 33 | DH1: 34 | DI1: 35 | DJ1: 36 | DK1: 37 | DL1: 38 | DM1: 39 | DN1: 40 | DO1: 41 | DP1: 42 | DQ1: 43 | DR1: 44 | DS1: 45 | DT1: 46 | DU1: 47 | DV1: 48 | DW1: 49 | DX1: 50 | DY1: 51 | DZ1: 52
A2: ● 사업명 : | B2: =+사업수지표!G3 -> 경기도 화성시 장짐리 공동주택 신축사업 | N2: 50 | O2: 개월 | Q2: 1 | R2: 2 | S2: 3 | T2: 4 | U2: 5 | V2: 6 | W2: 7 | X2: 8 | Y2: 9 | Z2: 10 | AA2: 11 | AB2: 12 | AC2: 13 | AD2: 14 | AE2: 15 | AF2: 16 | AG2: 17 | AH2: 18 | AI2: 19 | AJ2: 20 | AK2: 21 | AL2: 22 | AM2: 23 | AN2: 24 | AO2: 25 | AP2: 26 | AQ2: 27 | AR2: 28 | AS2: 29 | AT2: 30 | AU2: 31 | AV2: 32 | AW2: 33 | AX2: 34 | AY2: 35 | AZ2: 36 | BA2: 37 | BB2: 38 | BC2: 39 | BD2: 40 | BE2: 41 | BF2: 42 | BG2: 43 | BH2: 44 | BI2: 45 | BJ2: 46 | BK2: 47 | BL2: 48 | BM2: 49 | BN2: 50 | BO2: 51 | BP2: 52
A3: ● 공 기 : | B3: 37 | E3: 개월 | Q3: 1 | R3: 2 | S3: 3 | T3: 4 | U3: 5 | V3: 6 | W3: 7 | X3: 8 | Y3: 9 | Z3: 10 | AJ3: 신탁차입이자율 | AK3: =사업수지표!BD75 -> 0.0777 | AL3: PF수수료 | AM3: =사업수지표!BD80 -> 0 | AN3: 무이자 비중 | AP3: 무이자 이자율 | AQ3: =사업수지표!BD76 -> 0.042
A4: 내용(일정) | N4: 합계 | O4: 기집행 | P4: 신탁계약/PF | Q4: 준비 | R4: 준비 | S4: 준비 | T4: 준비 | U4: 준비 | V4: 준비 | W4: 준비 | X4: 준비 | Y4: 준비 | Z4: 준비 | AA4: 착공/분양 | AG4: 중도금1차 | AM4: 중도금2차 | AS4: 중도금3차 | AY4: 중도금4차 | BE4: 중도금 5차 | BI4: 중도금 6차 | BL4: 준공/입주 | BN4: 정산 | BY4: 합계
A5: 구 분 | Q5: D-10 | R5: D-9 | S5: D-8 | T5: D-7 | U5: D-6 | V5: D-5 | W5: D-4 | X5: D-3 | Y5: D-2 | Z5: D-1 | AA5: D | AB5: D+1 | AC5: D+2 | AD5: D+3 | AE5: D+4 | AF5: D+5 | AG5: D+6 | AH5: D+7 | AI5: D+8 | AJ5: D+9 | AK5: D+10 | AL5: D+11 | AM5: D+12 | AN5: D+13 | AO5: D+14 | AP5: D+15 | AQ5: D+16 | AR5: D+17 | AS5: D+18 | AT5: D+19 | AU5: D+20 | AV5: D+21 | AW5: D+22 | AX5: D+23 | AY5: D+24 | AZ5: D+25 | BA5: D+26 | BB5: D+27 | BC5: D+28 | BD5: D+29 | BE5: D+30 | BF5: D+31 | BG5: D+32 | BH5: D+33 | BI5: D+34 | BJ5: D+35 | BK5: D+36 | BL5: D+37 | BM5: 33 | BN5: 34 | BO5: 35 | BP5: 36 | BQ5: 37 | BR5: 38 | BS5: 39 | BT5: 40 | BU5: 41 | BV5: 40 | BW5: 41 | BX5: 42
A6: 시 기 | P6: 46082 | Q6: 46113 | R6: 46143 | S6: 46174 | T6: 46204 | U6: 46235 | V6: 46266 | W6: 46296 | X6: 46327 | Y6: 46357 | Z6: 46388 | AA6: 46419 | AB6: 46447 | AC6: 46478 | AD6: 46508 | AE6: 46539 | AF6: 46569 | AG6: 46600 | AH6: 46631 | AI6: 46661 | AJ6: 46692 | AK6: 46722 | AL6: 46753 | AM6: 46784 | AN6: 46813 | AO6: 46844 | AP6: 46874 | AQ6: 46905 | AR6: 46935 | AS6: 46966 | AT6: 46997 | AU6: 47027 | AV6: 47058 | AW6: 47088 | AX6: 47119 | AY6: 47150 | AZ6: 47178 | BA6: 47209 | BB6: 47239 | BC6: 47270 | BD6: 47300 | BE6: 47331 | BF6: 47362 | BG6: 47392 | BH6: 47423 | BI6: 47453 | BJ6: 47484 | BK6: 47515 | BL6: 47543 | BM6: 47574 | BN6: 47604 | BO6: 47635 | BP6: 47665 | BQ6: 47270 | BR6: 47300 | BS6: 47331 | BT6: 47362 | BU6: 47392 | BV6: 47423 | BW6: 47453 | BX6: =BW6+31 -> 47484
A7: 공정율 | B7: 공정율 | G7: 월계 | AA7: =공정률!F4 -> 0.0096 | AB7: =공정률!G4 -> 0.0096 | AC7: =공정률!H4 -> 0.0116 | AD7: =공정률!I4 -> 0.0116 | AE7: =공정률!J4 -> 0.0136 | AF7: =공정률!K4 -> 0.0136 | AG7: =공정률!L4 -> 0.0186 | AH7: =공정률!M4 -> 0.0186 | ... BL7: =공정률!AQ4 -> 0 | BY7: =SUM(P7:BS7) -> 1
G8: 누계 | N8: =+BY8 -> 1 | P8: 0 | X8: 0 | Y8: =X8+Y7 -> 0 | AA8: =AA7 -> 0.0096 | AB8: =AA8+AB7 -> 0.0192 | AC8: =AB8+AC7 -> 0.0308 | AD8: =AC8+AD7 -> 0.0424 | AE8: =AD8+AE7 -> 0.056 | AF8: =AE8+AF7 -> 0.0696 | AG8: =AF8+AG7 -> 0.0882 | AH8: =AG8+AH7 -> 0.1068 | AI8: =AH8+AI7 -> 0.1284 | ... BN8: =BM8+BN7 -> 1 | BO8: =BM8+BO7 -> 1 | BP8: =BO8+BP7 -> 1 | BQ8: =BP8+BQ7 -> 1 | BR8: =BQ8+BR7 -> 1 | BS8: =BR8+BS7 -> 1 | BT8: =BS8+BT7 -> 1 | BU8: =BT8+BU7 -> 1 | BV8: =BU8+BV7 -> 1 | BW8: =BV8+BW7 -> 1 | BX8: =BW8+BX7 -> 1 | BY8: =BX8 -> 1
A9: 분양률 | B9: =[28]사업수지표!B15 -> 아파트 | G9: 월별 | AA9: 0.2 | AB9: 0.1 | AC9: 0.05 | AD9: 0.05 | AE9: 0.1 | AF9: 0.03 | AG9: 0.02 | AH9: 0.04 | AI9: 0.03 | AJ9: 0.05 | AK9: 0.05 | AL9: 0.03 | AM9: 0.03 | AN9: 0.04 | AO9: 0.04 | AP9: 0.03 | AQ9: 0.03 | AR9: 0.01 | AS9: 0.01 | AT9: 0.01 | AU9: 0.01 | AV9: 0.01 | AW9: 0.01 | AX9: 0.01 | AY9: 0 | BI9: 0.01 | BY9: =SUM(P9:BS9) -> 1
G10: 누계 | N10: 1 | X10: =+P10+X9 -> 0 | Y10: =+X10+Y9 -> 0 | AA10: =X10+AA9 -> 0.2 | AB10: =AA10+AB9 -> 0.3 | AC10: =AB10+AC9 -> 0.35 | AD10: =AC10+AD9 -> 0.4 | AE10: =AD10+AE9 -> 0.5 | AF10: =AE10+AF9 -> 0.53 | AG10: =AF10+AG9 -> 0.55 | AH10: =AG10+AH9 -> 0.59 | AI10: =AH10+AI9 -> 0.62 | ... BX10: =BW10+BX9 -> 1 | BY10: =BX10 -> 1
A11: 분양률 | B11: =[28]사업수지표!#REF! -> #REF! | G11: 월별 | AL11: =VLOOKUP($N$1,#REF!,CQ1,FALSE) -> #REF! | AQ11: =VLOOKUP($N$1,#REF!,CR1,FALSE) -> #REF! | AR11: =VLOOKUP($N$1,#REF!,CS1,FALSE) -> #REF! | AS11: =VLOOKUP($N$1,#REF!,CT1,FALSE) -> #REF! | AT11: =VLOOKUP($N$1,#REF!,CU1,FALSE) -> #REF! | AU11: =VLOOKUP($N$1,#REF!,CV1,FALSE) -> #REF! | AV11: =VLOOKUP($N$1,#REF!,CW1,FALSE) -> #REF! | AW11: =VLOOKUP($N$1,#REF!,CX1,FALSE) -> #REF! | AX11: =VLOOKUP($N$1,#REF!,CY1,FALSE) -> #REF! | ... BN11: =VLOOKUP($N$1,#REF!,DO1,FALSE) -> #REF! | BO11: =VLOOKUP($N$1,#REF!,DO1,FALSE) -> #REF! | BP11: =VLOOKUP($N$1,#REF!,DP1,FALSE) -> #REF!
G12: 누계 | N12: 1 | X12: =+P12+X11 -> 0 | Y12: =+X12+Y11 -> 0 | AL12: =AL11 -> #REF! | AQ12: =+AL12+AQ11 -> #REF! | AR12: =+AQ12+AR11 -> #REF! | AS12: =+AR12+AS11 -> #REF! | AT12: =+AS12+AT11 -> #REF! | AU12: =+AT12+AU11 -> #REF! | AV12: =+AU12+AV11 -> #REF! | AW12: =+AV12+AW11 -> #REF! | AX12: =+AW12+AX11 -> #REF! | AY12: =+AX12+AY11 -> #REF! | ... BN12: =+BM12+BN11 -> #REF! | BO12: =+BM12+BO11 -> #REF! | BP12: =+BO12+BP11 -> #REF!
A13: 분양률 | B13: =[28]사업수지표!B23 -> 상가 | G13: 월별 | AQ13: 0.2 | AR13: 0.05 | AS13: 0.05 | AT13: 0.05 | AU13: 0.05 | AV13: 0.05 | AW13: 0.05 | AX13: 0.05 | AY13: 0.1 | AZ13: 0.05 | BA13: 0.05 | BB13: 0.05 | BC13: 0.05 | BD13: 0.05 | BF13: 0.05 | BH13: 0.05 | BY13: =SUM(P13:BR13) -> 1
G14: 누계 | N14: 1 | X14: =+P14+X13 -> 0 | Y14: =+X14+Y13 -> 0 | AK14: =SUM(AK13,AJ14) -> 0 | AL14: =SUM(AL13,AK14) -> 0 | AM14: =SUM(AM13,AL14) -> 0 | AP14: =SUM(AP13,AL14) -> 0 | AQ14: =SUM(AQ13,AP14) -> 0.2 | AR14: =SUM(AR13,AQ14) -> 0.25 | AS14: =SUM(AS13,AR14) -> 0.3 | AT14: =SUM(AT13,AS14) -> 0.35 | AU14: =SUM(AU13,AT14) -> 0.4 | AV14: =SUM(AV13,AU14) -> 0.45 | AW14: =SUM(AW13,AV14) -> 0.5 | AX14: =SUM(AX13,AW14) -> 0.55 | ... BN14: =SUM(BN13,BM14) -> 1 | BO14: =SUM(BO13,BM14) -> 1 | BP14: =SUM(BP13,BO14) -> 1 | BQ14: =SUM(BQ13,BP14) -> 1 | BR14: =SUM(BR13,BQ14) -> 1 | BS14: =SUM(BS13,BR14) -> 1 | BT14: =SUM(BT13,BS14) -> 1 | BU14: =SUM(BU13,BT14) -> 1 | BV14: =SUM(BV13,BU14) -> 1 | BW14: =SUM(BW13,BV14) -> 1 | BX14: =SUM(BX13,BW14) -> 1 | BY14: =BX14 -> 1
A15: 수입 | B15: =B9 -> 아파트 | G15: 계약금 | K15: 0.1 | N15: =K15*$N$23 -> 86803334 | AA15: =AA9*$N$15 -> 17360667 | AB15: =AB9*$N$15 -> 8680333.4 | AC15: =AC9*$N$15 -> 4340166.7 | AD15: =AD9*$N$15 -> 4340166.7 | AE15: =AE9*$N$15 -> 8680333.4 | AF15: =AF9*$N$15 -> 2604100 | AG15: =AG9*$N$15 -> 1736066.7 | AH15: =AH9*$N$15 -> 3472133.4 | ... BX15: =BX9*$N$15 -> 0 | BY15: =SUM(P15:BO15) -> 86803334 | BZ15: =BY15-N15 -> 0
G16: 1차중도금 | K16: 0.1 | N16: =K16*$N$23 -> 86803334 | AG16: =AG10*$N$16 -> 47741834 | AH16: =$N$16*AH9 -> 3472133.4 | AI16: =$N$16*AI9 -> 2604100 | AJ16: =$N$16*AJ9 -> 4340166.7 | AK16: =$N$16*AK9 -> 4340166.7 | AL16: =$N$16*AL9 -> 2604100 | AM16: =$N$16*AM9 -> 2604100 | AN16: =$N$16*AN9 -> 3472133.4 | AO16: =$N$16*AO9 -> 3472133.4 | ... BP16: =$N$16*BP9 -> 0 | BQ16: =BQ9*$N$16 -> 0 | BR16: =BR9*$N$16 -> 0 | BS16: =BS9*$N$16 -> 0 | BT16: =BT9*$N$16 -> 0 | BU16: =BU9*$N$16 -> 0 | BV16: =BV9*$N$16 -> 0 | BW16: =BW9*$N$16 -> 0 | BX16: =BX9*$N$16 -> 0 | BY16: =SUM(P16:BO16) -> 86803334 | BZ16: =BY16-N16 -> 0
G17: 2차중도금 | K17: 0.1 | N17: =K17*$N$23 -> 86803334 | AM17: =N17*AM10 -> 67706600 | AN17: =$N$17*AN9 -> 3472133.4 | AO17: =$N$17*AO9 -> 3472133.4 | AP17: =$N$17*AP9 -> 2604100 | AQ17: =$N$17*AQ9 -> 2604100 | AR17: =$N$17*AR9 -> 868033.34 | AS17: =$N$17*AS9 -> 868033.34 | AT17: =$N$17*AT9 -> 868033.34 | AU17: =$N$17*AU9 -> 868033.34 | ... BP17: =$N$17*BP9 -> 0 | BQ17: =BQ9*$N$17 -> 0 | BR17: =BR9*$N$17 -> 0 | BS17: =BS9*$N$17 -> 0 | BT17: =BT9*$N$17 -> 0 | BU17: =BU9*$N$17 -> 0 | BV17: =BV9*$N$17 -> 0 | BW17: =BW9*$N$17 -> 0 | BX17: =BX9*$N$17 -> 0 | BY17: =SUM(P17:BO17) -> 86803334 | BZ17: =BY17-N17 -> 0
G18: 3차중도금 | K18: 0.1 | N18: =K18*$N$23 -> 86803334 | AS18: =$N$18*AS10 -> 81595134 | AT18: =$N$18*AT9 -> 868033.34 | AU18: =$N$18*AU9 -> 868033.34 | AV18: =$N$18*AV9 -> 868033.34 | AW18: =$N$18*AW9 -> 868033.34 | AX18: =$N$18*AX9 -> 868033.34 | AY18: =$N$18*AY9 -> 0 | AZ18: =$N$18*AZ9 -> 0 | BA18: =$N$18*BA9 -> 0 | ... BP18: =$N$18*BP9 -> 0 | BQ18: =BQ9*$N$18 -> 0 | BR18: =BR9*$N$18 -> 0 | BS18: =BS9*$N$18 -> 0 | BT18: =BT9*$N$18 -> 0 | BU18: =BU9*$N$18 -> 0 | BV18: =BV9*$N$18 -> 0 | BW18: =BW9*$N$18 -> 0 | BX18: =BX9*$N$18 -> 0 | BY18: =SUM(P18:BO18) -> 86803334 | BZ18: =BY18-N18 -> 0
G19: 4차중도금 | K19: 0.1 | N19: =K19*$N$23 -> 86803334 | AY19: =AY10*N19 -> 85935301 | AZ19: =AZ9*$N$19 -> 0 | BA19: =BA9*$N$19 -> 0 | BB19: =BB9*$N$19 -> 0 | BC19: =BC9*$N$19 -> 0 | BD19: =BD9*$N$19 -> 0 | BE19: =BE9*$N$19 -> 0 | BF19: =BF9*$N$19 -> 0 | BG19: =BG9*$N$19 -> 0 | ... BX19: =BX9*$N$19 -> 0 | BY19: =SUM(P19:BO19) -> 86803334 | BZ19: =BY19-N19 -> 0
G20: 5차중도금 | K20: 0.1 | N20: =K20*$N$23 -> 86803334 | BE20: =BE10*$N$20 -> 85935301 | BF20: =BF9*$N$20 -> 0 | BG20: =BG9*$N$20 -> 0 | BH20: =BH9*$N$20 -> 0 | BI20: =BI9*$N$20 -> 868033.34 | BJ20: =BJ9*$N$20 -> 0 | BK20: =BK9*$N$20 -> 0 | BL20: =BL9*$N$20 -> 0 | BM20: =BM9*$N$20 -> 0 | ... BX20: =BX9*$N$20 -> 0 | BY20: =SUM(P20:BO20) -> 86803334 | BZ20: =BY20-N20 -> 0
G21: 6차중도금 | K21: 0.1 | N21: =K21*$N$23 -> 86803334 | BI21: =BI10*$N$21 -> 86803334 | BJ21: =BJ9*$N$21 -> 0 | BK21: =BK9*$N$21 -> 0 | BL21: =BL9*$N$21 -> 0 | BM21: =BM9*$N$21 -> 0 | BN21: =BN9*$N$21 -> 0 | BO21: =BO9*$N$21 -> 0 | BP21: =BP9*$N$21 -> 0 | BQ21: =BQ9*$N$21 -> 0 | ... BX21: =BX9*$N$21 -> 0 | BY21: =SUM(P21:BO21) -> 86803334 | BZ21: =BY21-N21 -> 0
G22: 잔 금 | K22: 0.3 | N22: =K22*$N$23 -> 2.6041e+08 | BL22: =N22*50% -> 1.30205e+08 | BM22: =N22*50% -> 1.30205e+08 | BP22: =BP9*N22 -> 0 | BQ22: =BQ9*$N$22 -> 0 | BU22: =BU10*Y22 -> 0 | BV22: =BV10*AH22 -> 0 | BW22: =BW10*AI22 -> 0 | BX22: =BX10*AJ22 -> 0 | BY22: =SUM(P22:BO22) -> 2.6041e+08 | BZ22: =BY22-N22 -> 0
G23: 소계 | N23: =사업수지표!AL18 -> 8.6803334e+08 | P23: =SUM(P15:P22) -> 0 | R23: =SUM(R15:R22) -> 0 | S23: =SUM(S15:S22) -> 0 | T23: =SUM(T15:T22) -> 0 | U23: =SUM(U15:U22) -> 0 | V23: =SUM(V15:V22) -> 0 | W23: =SUM(W15:W22) -> 0 | X23: =SUM(X15:X22) -> 0 | Y23: =SUM(Y15:Y22) -> 0 | ... BX23: =SUM(BX15:BX22) -> 0 | BY23: =SUM(P23:BO23) -> 8.6803334e+08 | BZ23: =BY23-N23 -> 0
B24: =B11 -> #REF! | G24: 계약금 | K24: 0.1 | N24: =사업수지표!AL19 -> 4399666 | AL24: =$N$24*AL11 -> #REF! | AQ24: =$N$24*AQ11 -> #REF! | AR24: =$N$24*AR11 -> #REF! | AS24: =$N$24*AS11 -> #REF! | AT24: =$N$24*AT11 -> #REF! | AU24: =$N$24*AU11 -> #REF! | AV24: =$N$24*AV11 -> #REF! | AW24: =$N$24*AW11 -> #REF! | AX24: =$N$24*AX11 -> #REF! | ... BP24: =$N$24*BP11 -> #REF! | BY24: 0.0268 | BZ24: =BY24-N24 -> -4399666
G25: 1차중도금 | K25: 0.1 | N25: =사업수지표!AL20 -> 3176318.5 | AS25: =$N$25*AS12 -> #REF! | AT25: =$N$25*AT11 -> #REF! | AU25: =$N$25*AU11 -> #REF! | AV25: =$N$25*AV11 -> #REF! | AW25: =$N$25*AW11 -> #REF! | AX25: =$N$25*AX11 -> #REF! | AY25: =$N$25*AY11 -> #REF! | AZ25: =$N$25*AZ11 -> #REF! | BA25: =$N$25*BA11 -> #REF! | ... BP25: =$N$25*BP11 -> #REF! | BY25: 0.0268 | BZ25: =BY25-N25 -> -3176318.5
G26: 2차중도금 | K26: 0.1 | N26: =사업수지표!AL21 -> 7575984.5 | AV26: =$N$26*AV12 -> #REF! | AW26: =$N$26*AW11 -> #REF! | AX26: =$N$26*AX11 -> #REF! | AY26: =$N$26*AY11 -> #REF! | AZ26: =$N$26*AZ11 -> #REF! | BA26: =$N$26*BA11 -> #REF! | BB26: =$N$26*BB11 -> #REF! | BC26: =$N$26*BC11 -> #REF! | BD26: =$N$26*BD11 -> #REF! | ... BP26: =$N$26*BP11 -> #REF! | BY26: 0.0268 | BZ26: =BY26-N26 -> -7575984.5
G27: 3차중도금 | K27: 0.1 | N27: =사업수지표!AL22 -> 41470000 | AY27: =$N$27*AY12 -> #REF! | AZ27: =$N$27*AZ11 -> #REF! | BA27: =$N$27*BA11 -> #REF! | BB27: =$N$27*BB11 -> #REF! | BC27: =$N$27*BC11 -> #REF! | BD27: =$N$27*BD11 -> #REF! | BE27: =$N$27*BE11 -> #REF! | BF27: =$N$27*BF11 -> #REF! | BG27: =$N$27*BG11 -> #REF! | ... BP27: =$N$27*BP11 -> #REF! | BY27: 0.0268 | BZ27: =BY27-N27 -> -41470000
G28: 4차중도금 | K28: 0.1 | N28: =사업수지표!AL23 -> 9.1707932e+08 | BB28: =$N$28*BB12 -> #REF! | BC28: =$N$28*BC11 -> #REF! | BD28: =$N$28*BD11 -> #REF! | BE28: =$N$28*BE11 -> #REF! | BF28: =$N$28*BF11 -> #REF! | BG28: =$N$28*BG11 -> #REF! | BH28: =$N$28*BH11 -> #REF! | BI28: =$N$28*BI11 -> #REF! | BJ28: =$N$28*BJ11 -> #REF! | ... BP28: =$N$28*BP11 -> #REF! | BY28: 0.0268 | BZ28: =BY28-N28 -> -9.1707932e+08
G29: 5차중도금 | K29: 0.1 | N29: =사업수지표!AL24 -> 96000000 | BE29: =$N$29*BE12 -> #REF! | BF29: =$N$29*BF11 -> #REF! | BG29: =$N$29*BG11 -> #REF! | BH29: =$N$29*BH11 -> #REF! | BI29: =$N$29*BI11 -> #REF! | BJ29: =$N$29*BJ11 -> #REF! | BK29: =$N$29*BK11 -> #REF! | BL29: =$N$29*BL11 -> #REF! | BM29: =$N$29*BM11 -> #REF! | ... BP29: =$N$29*BP11 -> #REF! | BY29: 0.0268 | BZ29: =BY29-N29 -> -96000000
G30: 6차중도금 | K30: 0.1 | N30: =사업수지표!AL25 -> 13969158 | BH30: =$N$30*BH12 -> #REF! | BI30: =$N$30*BI11 -> #REF! | BJ30: =$N$30*BJ11 -> #REF! | BK30: =$N$30*BK11 -> #REF! | BL30: =$N$30*BL11 -> #REF! | BM30: =$N$30*BM11 -> #REF! | BN30: =$N$30*BN11 -> #REF! | BO30: =$N$30*BO11 -> #REF! | BP30: =$N$30*BP11 -> #REF! | BY30: 0.0268 | BZ30: =BY30-N30 -> -13969158
G31: 잔 금 | K31: 0.3 | N31: =사업수지표!AL28 -> 1603249 | BK31: =$N$31*BK12*5% -> #REF! | BL31: =$N$31*BL12*40% -> #REF! | BM31: =$N$31*BM12*55% -> #REF! | BN31: =$N$31*BN12*55% -> #REF! | BY31: 0.0268 | BZ31: =BY31-N31 -> -1603249
G32: 소계 | N32: =사업수지표!AL29 -> 3882030.6 | X32: =SUM(X24:X31) -> 0 | Y32: =SUM(Y24:Y31) -> 0 | AH32: =SUM(AH24:AH31) -> 0 | AI32: =SUM(AI24:AI31) -> 0 | AJ32: =SUM(AJ24:AJ31) -> 0 | AK32: =SUM(AK24:AK31) -> 0 | AL32: =SUM(AL24:AL31) -> #REF! | AQ32: =SUM(AQ24:AQ31) -> #REF! | AR32: =SUM(AR24:AR31) -> #REF! | AS32: =SUM(AS24:AS31) -> #REF! | AT32: =SUM(AT24:AT31) -> #REF! | AU32: =SUM(AU24:AU31) -> #REF! | AV32: =SUM(AV24:AV31) -> #REF! | AW32: =SUM(AW24:AW31) -> #REF! | AX32: =SUM(AX24:AX31) -> #REF! | ... BP32: =SUM(BP24:BP31) -> #REF! | BY32: 0.0268 | BZ32: =BY32-N32 -> -3882030.6
B33: =B13 -> 상가 | G33: 계약금 | K33: 0.1 | N33: =K33*$N$39 -> 757598.45 | AQ33: =N33*AQ13 -> 151519.69 | AR33: =N33*AR13 -> 37879.923 | AS33: =N33*AS13 -> 37879.923 | AT33: =N33*AT13 -> 37879.923 | AU33: =N33*AU13 -> 37879.923 | AV33: =$N$33*AV13 -> 37879.923 | AW33: =$N$33*AW13 -> 37879.923 | AX33: =$N$33*AX13 -> 37879.923 | AY33: =$N$33*AY13 -> 75759.845 | AZ33: =$N$33*AZ13 -> 37879.923 | BA33: =$N$33*BA13 -> 37879.923 | BB33: =$N$33*BB13 -> 37879.923 | BC33: =$N$33*BC13 -> 37879.923 | ... BK33: =$N$33*BK13 -> 0 | BS33: =BS13*$N$33 -> 0 | BT33: =BT13*$N$33 -> 0 | BU33: =BU13*$N$33 -> 0 | BV33: =BV13*$N$33 -> 0 | BW33: =BW13*$N$33 -> 0 | BX33: =BX13*$N$33 -> 0 | BY33: =SUM(P33:BO33) -> 757598.45 | BZ33: =BY33-N33 -> 0
G34: 1차중도금 | K34: 0.1 | N34: =K34*$N$39 -> 757598.45 | AV34: =N34*AV14 -> 340919.3 | AW34: =N34*AW13 -> 37879.923 | AX34: =N34*AX13 -> 37879.923 | AY34: =N34*AY13 -> 75759.845 | AZ34: =N34*AZ13 -> 37879.923 | BA34: =N34*BA13 -> 37879.923 | BB34: =N34*BB13 -> 37879.923 | BC34: =N34*BC13 -> 37879.923 | BD34: =N34*BD13 -> 37879.923 | BE34: =N34*BE13 -> 0 | BF34: =N34*BF13 -> 37879.923 | BG34: =N34*BG13 -> 0 | BH34: =N34*BH13 -> 37879.923 | BI34: =X34*BI13 -> 0 | BJ34: =Y34*BJ13 -> 0 | BY34: =SUM(P34:BO34) -> 757598.45 | BZ34: =BY34-N34 -> 0
G35: 2차중도금 | K35: 0.1 | N35: =K35*$N$39 -> 757598.45 | BA35: =N35*BA14 -> 568198.84 | BB35: =N35*BB13 -> 37879.923 | BC35: =N35*BC13 -> 37879.923 | BD35: =N35*BD13 -> 37879.923 | BF35: =N35*BF13 -> 37879.923 | BH35: =N35*BH13 -> 37879.923 | BY35: =SUM(P35:BO35) -> 757598.45 | BZ35: =BY35-N35 -> 0
G36: 3차중도금 | K36: 0.1 | N36: =K36*$N$39 -> 757598.45 | BE36: =N36*BE14 -> 681838.61 | BF36: =N36*BF13 -> 37879.923 | BH36: =N36*BH13 -> 37879.923 | BY36: =SUM(P36:BO36) -> 757598.45 | BZ36: =BY36-N36 -> 0
G37: 4차중도금 | K37: 0.1 | N37: =K37*$N$39 -> 757598.45 | BI37: =N37*BI14 -> 757598.45 | BY37: =SUM(P37:BO37) -> 757598.45 | BZ37: =BY37-N37 -> 0
G38: 잔 금 | K38: 0.5 | N38: =K38*$N$39 -> 3787992.2 | BL38: =N38*50% -> 1893996.1 | BM38: =N38*50% -> 1893996.1 | BY38: =SUM(P38:BO38) -> 3787992.2 | BZ38: =BY38-N38 -> 0
G39: 소계 | N39: =사업수지표!AL21 -> 7575984.5 | AP39: =SUM(AP33:AP38) -> 0 | AQ39: =SUM(AQ33:AQ38) -> 151519.69 | AR39: =SUM(AR33:AR38) -> 37879.923 | AS39: =SUM(AS33:AS38) -> 37879.923 | AT39: =SUM(AT33:AT38) -> 37879.923 | AU39: =SUM(AU33:AU38) -> 37879.923 | AV39: =SUM(AV33:AV38) -> 378799.22 | AW39: =SUM(AW33:AW38) -> 75759.845 | ... BX39: =SUM(BX33:BX38) -> 0 | BY39: =SUM(P39:BO39) -> 7575984.5 | BZ39: =BY39-N39 -> 0
B40: =[28]사업수지표!B25 -> 발코니 확장 | G40: 계약금 | K40: 0.1 | N40: =N42*K40 -> 4147000 | AA40: =AA9*$N$40 -> 829400 | AB40: =AB9*$N$40 -> 414700 | AC40: =AC9*$N$40 -> 207350 | AD40: =AD9*$N$40 -> 207350 | AE40: =AE9*$N$40 -> 414700 | AF40: =AF9*$N$40 -> 124410 | AG40: =AG9*$N$40 -> 82940 | AH40: =AH9*$N$40 -> 165880 | ... BP40: =BP9*$N$40 -> 0 | BQ40: =BQ9*N40 -> 0 | BR40: =$N$40*BR9*10% -> 0 | BS40: =$N$40*BS9*10% -> 0 | BT40: =$N$40*BT9*10% -> 0 | BU40: =$N$40*BU9*10% -> 0 | BV40: =$N$40*BV9*10% -> 0 | BW40: =$N$40*BW9*10% -> 0 | BX40: =$N$40*BX9*10% -> 0 | BY40: =SUM(P40:BO40) -> 4147000 | BZ40: =BY40-N40 -> 0
G41: 잔금 | K41: 0.9 | N41: =N42*K41 -> 37323000 | BL41: =N41*50% -> 18661500 | BM41: =N41*50% -> 18661500 | BY41: =SUM(P41:BO41) -> 37323000
G42: 소계 | N42: =사업수지표!AL22 -> 41470000 | P42: =SUM(P40:P41) -> 0 | Q42: =SUM(Q40:Q41) -> 0 | R42: =SUM(R40:R41) -> 0 | S42: =SUM(S40:S41) -> 0 | T42: =SUM(T40:T41) -> 0 | U42: =SUM(U40:U41) -> 0 | V42: =SUM(V40:V41) -> 0 | W42: =SUM(W40:W41) -> 0 | ... BJ42: =SUM(BJ40:BJ41) -> 0 | BL42: =SUM(BL40:BL41) -> 18661500 | BM42: =SUM(BM40:BM41) -> 18661500 | BN42: =SUM(BN40:BN41) -> 0 | BO42: =SUM(BO40:BO41) -> 0 | BP42: =SUM(BP40:BP41) -> 0 | BY42: =SUM(P42:BO42) -> 41470000
B43: 매 출 합 계 | N43: =사업수지표!AL23 -> 9.1707932e+08 | P43: =SUM(P23,P39:P40) -> 0 | X43: =SUM(X23,X39:X40) -> 0 | Y43: =SUM(Y23,Y39:Y40) -> 0 | AA43: =SUM(AA23,AA39,AA42) -> 18190067 | AB43: =SUM(AB23,AB39,AB42) -> 9095033.4 | AC43: =SUM(AC23,AC39,AC42) -> 4547516.7 | AD43: =SUM(AD23,AD39,AD42) -> 4547516.7 | AE43: =SUM(AE23,AE39,AE42) -> 9095033.4 | AF43: =SUM(AF23,AF39,AF42) -> 2728510 | AG43: =SUM(AG23,AG39,AG42) -> 49560840 | AH43: =SUM(AH23,AH39,AH42) -> 7110146.7 | ... BX43: =SUM(BX23,BX39,BX42) -> 0 | BY43: =SUM(P43:BX43) -> 9.1707932e+08 | BZ43: =BY43-N43 -> 0 | CA43: =BY43/N43 -> 1
A44: 비 용 | B44: 토지비 | D44: =사업수지표!G24 -> 채권매입비용 | N44: =사업수지표!Z24 -> 96000000 | O44: =사업수지표!AR24 -> 0 | P44: =N44 -> 96000000 | BY44: =SUM(O44:BQ44) -> 96000000 | BZ44: =BY44-N44 -> 0
D45: =사업수지표!G25 -> 토지비(공동주택) | N45: =사업수지표!AL25 -> 13969158 | O45: =사업수지표!AR25 -> 0 | P45: =N45 -> 13969158 | BY45: =SUM(O45:BQ45) -> 13969158 | BZ45: =BY45-N45 -> 0
D46: =사업수지표!G26 -> 토지비(기반시설부지) | N46: =사업수지표!AL26 -> 11960903 | P46: =N46 -> 11960903 | BY46: =SUM(O46:BQ46) -> 11960903
D47: =사업수지표!G27 -> 토지비(211,222-2번지) | N47: =사업수지표!AL27 -> 7470960 | P47: =N47 -> 7470960 | BY47: =SUM(O47:BQ47) -> 7470960
D48: =사업수지표!G28 -> 취등록세 | N48: =사업수지표!AL28 -> 1603249 | O48: =사업수지표!AR28 -> 0 | P48: =사업수지표!AS28 -> 1603249 | BY48: =SUM(O48:BQ48) -> 1603249 | BZ48: =BY48-N48 -> 0
D49: =사업수지표!G29 -> 명도 및 보상비 | N49: =사업수지표!AL29 -> 3882030.6 | O49: =사업수지표!AR29 -> 0 | P49: =N49 -> 3882030.6 | BY49: =SUM(O49:BQ49) -> 3882030.6 | BZ49: =BY49-N49 -> 0
D50: =사업수지표!G31 -> 인허가 비용 | N50: =사업수지표!Z31 -> 5444723 | O50: =사업수지표!AR31 -> 5444723 | BY50: =SUM(O50:BQ50) -> 5444723
D51: =사업수지표!G30 -> 주식근질권해제비용 | N51: =사업수지표!AS30 -> 5000000 | P51: =N51 -> 5000000 | BY51: =SUM(O51:BQ51) -> 5000000
D52: 소계 | N52: =SUM(N44:N51) -> 1.4533102e+08 | O52: =SUM(O44:O50) -> 5444723 | P52: =SUM(P44:P51) -> 1.398863e+08 | X52: =SUM(X44:X49) -> 0 | Y52: =SUM(Y44:Y51) -> 0 | Z52: =SUM(Z44:Z51) -> 0 | AA52: =SUM(AA44:AA51) -> 0 | AB52: =SUM(AB44:AB51) -> 0 | AC52: =SUM(AC44:AC51) -> 0 | AD52: =SUM(AD44:AD51) -> 0 | AE52: =SUM(AE44:AE51) -> 0 | AF52: =SUM(AF44:AF51) -> 0 | ... BP52: =SUM(BP44:BP51) -> 0 | BQ52: =SUM(BQ44:BQ49) -> 0 | BR52: =SUM(BR44:BR49) -> 0 | BS52: =SUM(BS44:BS49) -> 0 | BT52: =SUM(BT44:BT49) -> 0 | BU52: =SUM(BU44:BU49) -> 0 | BV52: =SUM(BV44:BV49) -> 0 | BW52: =SUM(BW44:BW49) -> 0 | BX52: =SUM(BX44:BX49) -> 0 | BY52: =SUM(BY44:BY51) -> 1.4533102e+08 | BZ52: =BY52-N52 -> 0 | CA52: =BY52=SUM(O52:BX52) -> TRUE
B53: 건축비 | D53: =사업수지표!G33 -> 직접공사비(본공사) | N53: =+사업수지표!AL33 -> 4.4039982e+08 | O53: 0 | AA53: =AA138 -> 3805054.5 | AB53: =AB138 -> 3805054.5 | AC53: =AC138 -> 4597774.1 | AD53: =AD138 -> 4597774.1 | AE53: =AE138 -> 5390493.8 | AF53: =AF138 -> 5390493.8 | AG53: =AG138 -> 7372293 | AH53: =AH138 -> 7372293 | ... BL53: =BL138 -> 0 | BM53: =BM137 -> 0 | BN53: =N53*10% -> 44039982 | BQ53: =BQ139 -> 0 | BR53: =BR138 -> 0 | BS53: =BS138 -> 0 | BT53: =BT138 -> 0 | BU53: =BU138 -> 0 | BV53: =BV138 -> 0 | BW53: =BW138 -> 0 | BX53: =BX139 -> 0 | BY53: =SUM(O53:BQ53) -> 4.4039982e+08 | BZ53: =BY53-N53 -> 0
D54: =사업수지표!G34 -> 기타공사비(본공사) | N54: =사업수지표!AL34 -> 0 | O54: =사업수지표!AR34 -> 0 | BY54: =SUM(O54:BQ54) -> 0 | BZ54: =BY54-N54 -> 0
D55: =사업수지표!G35 -> 각종인입비 | N55: =+사업수지표!AL35 -> 2965293.2 | O55: 0 | BJ55: =$N$55/2 -> 1482646.6 | BK55: 1482647 | BY55: =SUM(O55:BQ55) -> 2965293.6 | BZ55: =BY55-N55 -> 0.38015
D56: =사업수지표!G36 -> 조건부이행공사비 | N56: =+사업수지표!AL36 -> 7042054.8 | O56: 0 | AH56: =N56*20% -> 1408411 | AM56: =N56*20% -> 1408411 | AQ56: =N56*20% -> 1408411 | AV56: =$N$56/5 -> 1408411 | AZ56: =$N$56/5 -> 1408411 | BY56: =SUM(O56:BQ56) -> 7042054.8 | BZ56: =BY56-N56 -> 0
D57: =사업수지표!G37 -> 예술장식품비 | N57: =+사업수지표!AL37 -> 754147.96 | O57: =사업수지표!AR37 -> 0 | P57: =사업수지표!$AS$37/2 -> 0 | X57: =사업수지표!$AS$37/2 -> 0 | BG57: =N57*10% -> 75414.796 | BH57: =N57*80% -> 603318.37 | BJ57: =N57*10% -> 75414.796 | BY57: =SUM(O57:BQ57) -> 754147.96 | BZ57: =BY57-N57 -> 0
D58: 소계 | N58: =SUM(N53:N57) -> 4.5116132e+08 | O58: =SUM(O53:O57) -> 0 | P58: =SUM(P53:P57) -> 0 | Q58: =SUM(Q53:Q57) -> 0 | R58: =SUM(R53:R57) -> 0 | S58: =SUM(S53:S57) -> 0 | T58: =SUM(T53:T57) -> 0 | U58: =SUM(U53:U57) -> 0 | ... BY58: =SUM(BY53:BY57) -> 4.5116132e+08 | BZ58: =BY58-N58 -> 0.38015032 | CA58: =SUM(P58:BX58)-BY58 -> 0
B59: 용역비 | D59: =사업수지표!G39 -> 설계비 | N59: =+사업수지표!AL39 -> 4804800 | O59: =사업수지표!AR39 -> 480480 | AL59: 480480 | AQ59: 240240 | AV59: 240240 | BA59: 480480 | BE59: 960960 | BI59: 1441440 | BL59: 480480 | BY59: =SUM(O59:BQ59) -> 4804800 | BZ59: =BY59-N59 -> 0
D60: =사업수지표!G40 -> 감리비 | N60: =+사업수지표!AL40 -> 10872742 | O60: =사업수지표!AR40 -> 0 | Z60: =N60*0.1 -> 1087274.2 | AI60: =(N60*0.8)/10 -> 869819.35 | AL60: =(N60*0.8)/10 -> 869819.35 | AO60: =(N60*0.8)/10 -> 869819.35 | AR60: =(N60*0.8)/10 -> 869819.35 | AU60: =(N60*0.8)/10 -> 869819.35 | AX60: =(N60*0.8)/10 -> 869819.35 | BA60: =(N60*0.8)/10 -> 869819.35 | BD60: =(N60*0.8)/10 -> 869819.35 | BG60: =(N60*0.8)/10 -> 869819.35 | BJ60: =(N60*0.8)/10 -> 869819.35 | BM60: =N60*0.1 -> 1087274.2 | BY60: =SUM(O60:BQ60) -> 10872742 | BZ60: =BY60-N60 -> 0
D61: =사업수지표!G41 -> 미매입 토지 용역비 | N61: =+사업수지표!AL41 -> 0 | O61: =사업수지표!AR41 -> 0 | BY61: =SUM(O61:BQ61) -> 0 | BZ61: =BY61-N61 -> 0
BY62: =SUM(O62:BQ62) -> 0
D63: =사업수지표!G42 -> 지구단위 용역비 | N63: =+사업수지표!AL42 -> 1925000 | O63: =사업수지표!AR42 -> 660000 | AA63: 632500 | AB63: 632500 | BY63: =SUM(O63:BQ63) -> 1925000 | BZ63: =BY63-N63 -> 0
D64: 소계 | N64: =SUM(N59:N63) -> 17602542 | O64: =SUM(O59:O63) -> 1140480 | P64: =SUM(P59:P63) -> 0 | X64: =SUM(X59:X63) -> 0 | Y64: =SUM(Y59:Y63) -> 0 | Z64: =SUM(Z59:Z63) -> 1087274.2 | AA64: =SUM(AA59:AA63) -> 632500 | AB64: =SUM(AB59:AB63) -> 632500 | AC64: =SUM(AC59:AC63) -> 0 | AD64: =SUM(AD59:AD63) -> 0 | AE64: =SUM(AE59:AE63) -> 0 | ... BK64: =SUM(BK59:BK63) -> 0 | BL64: =SUM(BL59:BL61) -> 480480 | BM64: =SUM(BM59:BM61) -> 1087274.2 | BN64: =SUM(BN59:BN61) -> 0 | BO64: =SUM(BO59:BO61) -> 0 | BP64: =SUM(BP59:BP61) -> 0 | BQ64: =SUM(BQ59:BQ61) -> 0 | BR64: =SUM(BR59:BR61) -> 0 | BS64: =SUM(BS59:BS61) -> 0 | ... BX64: =SUM(BX59:BX61) -> 0 | BY64: =SUM(BY59:BY63) -> 17602542 | BZ64: =BY64-N64 -> 0 | CA64: =SUM(O64:BX64)-BY64 -> 0
B65: 판매비 | D65: =사업수지표!G44 -> M/H부지임차비 | N65: =사업수지표!AL44 -> 792000 | O65: =사업수지표!AR44 -> 0 | P65: 0 | X65: =$N$65/24 -> 33000 | Y65: =$N$65/24 -> 33000 | Z65: =$N$65/24 -> 33000 | AA65: =$N$65/24 -> 33000 | AB65: =$N$65/24 -> 33000 | AC65: =$N$65/24 -> 33000 | AD65: =$N$65/24 -> 33000 | AE65: =$N$65/24 -> 33000 | ... AU65: =$N$65/24 -> 33000 | BY65: =SUM(O65:BQ65) -> 792000 | BZ65: =BY65-N65 -> 0
D66: =사업수지표!G45 -> M/H건립비 | N66: =사업수지표!AL45 -> 1815000 | O66: =사업수지표!AR45 -> 0 | X66: =N66/3 -> 605000 | Y66: =N66/3 -> 605000 | Z66: =N66/3 -> 605000 | BY66: =SUM(O66:BQ66) -> 1815000 | BZ66: =BY66-N66 -> 0
D67: =사업수지표!G46 -> M/H운영비 | N67: =사업수지표!AL46 -> 693000 | O67: =사업수지표!AR46 -> 0 | P67: =사업수지표!AR46 -> 0 | X67: 0 | AA67: =$N$67/21 -> 33000 | AB67: =$N$67/21 -> 33000 | AC67: =$N$67/21 -> 33000 | AD67: =$N$67/21 -> 33000 | AE67: =$N$67/21 -> 33000 | AF67: =$N$67/21 -> 33000 | AG67: =$N$67/21 -> 33000 | AH67: =$N$67/21 -> 33000 | ... AU67: =$N$67/21 -> 33000 | BY67: =SUM(O67:BQ67) -> 693000 | BZ67: =BY67-N67 -> 0
D68: =사업수지표!G47 -> 광고홍보비 | N68: =사업수지표!AL47 -> 10039288 | O68: =사업수지표!AR47 -> 0 | P68: 0 | X68: =N68*5% -> 501964.42 | Y68: =N68*2.5% -> 250982.21 | Z68: =N68*2.5% -> 250982.21 | AA68: =N68*30% -> 3011786.5 | AL68: =N68*10% -> 1003928.8 | AQ68: =N68*10% -> 1003928.8 | AV68: =N68*10% -> 1003928.8 | BA68: =N68*10% -> 1003928.8 | BE68: =N68*10% -> 1003928.8 | BI68: =N68*10% -> 1003928.8 | BY68: =SUM(O68:BQ68) -> 10039288 | BZ68: =BY68-N68 -> 0
D69: =사업수지표!G48 -> 분양보증 수수료 | N69: =사업수지표!AL48 -> 3747010.6 | O69: =사업수지표!AR48 -> 0 | P69: =사업수지표!AR48 -> 0 | X69: 0 | AA69: =$N$69 -> 3747010.6 | BY69: =SUM(O69:BQ69) -> 3747010.6 | BZ69: =BY69-N69 -> 0
D70: =사업수지표!G49 -> 분양수수료(공동주택) | N70: =사업수지표!AL49 -> 10367500 | O70: =사업수지표!AR49 -> 0 | P70: =사업수지표!AR49 -> 0 | X70: 0 | AH70: =$N$70*AH10 -> 6116825 | AI70: =$N$70*AI9 -> 311025 | AJ70: =$N$70*AJ9 -> 518375 | AK70: =$N$70*AK9 -> 518375 | AL70: =$N$70*AL9 -> 311025 | AM70: =$N$70*AM9 -> 311025 | AN70: =$N$70*AN9 -> 414700 | AO70: =$N$70*AO9 -> 414700 | AP70: =$N$70*AP9 -> 311025 | ... BS70: =$N$70*BS9 -> 0 | BY70: =SUM(O70:BQ70) -> 10367500 | BZ70: =BY70-N70 -> 0
D71: =사업수지표!G50 -> 분양수수료(근생) | N71: =사업수지표!AL50 -> 609773.69 | O71: =사업수지표!AR50 -> 0 | P71: =사업수지표!AR50 -> 0 | X71: 0 | Y71: =$N$71*Y13 -> 0 | AH71: =$N$71*AH13 -> 0 | AI71: =$N$71*AI13 -> 0 | AJ71: =$N$71*AJ13 -> 0 | AK71: =$N$71*AK13 -> 0 | AL71: =$N$71*AL13 -> 0 | AM71: =$N$71*AM13 -> 0 | AN71: =$N$71*AN13 -> 0 | AO71: =$N$71*AO13 -> 0 | ... BR71: =$N$71*BR13 -> 0 | BY71: =SUM(O71:BQ71) -> 609773.69 | BZ71: =BY71-N71 -> 0
D72: =사업수지표!G51 -> 분양촉진비 | N72: =사업수지표!AL51 -> 6220500 | O72: =사업수지표!AR51 -> 0 | AP72: =N72*40% -> 2488200 | AV72: =N72*30% -> 1866150 | BA72: =N72*30% -> 1866150 | BY72: =SUM(O72:BQ72) -> 6220500 | BZ72: =BY72-N72 -> 0
D73: 소계 | N73: =SUM(N65:N72) -> 34284073 | O73: =SUM(O65:O72) -> 0 | P73: =SUM(P65:P72) -> 0 | Q73: =SUM(Q65:Q72) -> 0 | R73: =SUM(R65:R72) -> 0 | S73: =SUM(S65:S72) -> 0 | T73: =SUM(T65:T72) -> 0 | U73: =SUM(U65:U72) -> 0 | ... BQ73: =SUM(BQ65:BQ72) -> 0 | BR73: =SUM(BR65:BR71) -> 0 | BS73: =SUM(BS65:BS71) -> 0 | BT73: =SUM(BT65:BT71) -> 0 | BU73: =SUM(BU65:BU71) -> 0 | BV73: =SUM(BV65:BV71) -> 0 | BW73: =SUM(BW65:BW71) -> 0 | BX73: =SUM(BX65:BX71) -> 0 | BY73: =SUM(BY65:BY72) -> 34284073 | BZ73: =BY73-N73 -> 0 | CA73: =SUM(O73:BX73)-BY73 -> 0
B74: 부대비 | D74: =사업수지표!G53 -> 신탁보수 | N74: =사업수지표!AL53 -> 27379878 | O74: =사업수지표!AR53 -> 0 | P74: =사업수지표!AS53 -> 2737987.8 | AA74: =N74*10% -> 2737987.8 | AL74: =N74*10% -> 2737987.8 | AQ74: =N74*10% -> 2737987.8 | AV74: =N74*10% -> 2737987.8 | BA74: =N74*10% -> 2737987.8 | BE74: =N74*10% -> 2737987.8 | BI74: =N74*10% -> 2737987.8 | BL74: =N74*10% -> 2737987.8 | BN74: =N74*10% -> 2737987.8 | BY74: =SUM(O74:BQ74) -> 27379878 | BZ74: =BY74-N74 -> 0
D75: =사업수지표!G54 -> 0 | N75: =사업수지표!AL54 -> 0 | O75: =사업수지표!AR54 -> 0 | P75: =N75 -> 0 | BY75: =SUM(O75:BQ75) -> 0 | BZ75: =BY75-N75 -> 0
D76: =사업수지표!G55 -> 시행사운영비 | N76: =사업수지표!AL55 -> 1850000 | O76: =사업수지표!AR55 -> 0 | AA76: =사업수지표!$AW$55 -> 50000 | AB76: =사업수지표!$AW$55 -> 50000 | AC76: =사업수지표!$AW$55 -> 50000 | AD76: =사업수지표!$AW$55 -> 50000 | AE76: =사업수지표!$AW$55 -> 50000 | AF76: =사업수지표!$AW$55 -> 50000 | AG76: =사업수지표!$AW$55 -> 50000 | AH76: =사업수지표!$AW$55 -> 50000 | ... BK76: =사업수지표!$AW$55 -> 50000 | BY76: =SUM(O76:BQ76) -> 1850000 | BZ76: =BY76-N76 -> 0
D77: =사업수지표!G56 -> 0 | N77: =사업수지표!AL56 -> 0 | O77: =사업수지표!AR56 -> 0 | P77: =사업수지표!AR56 -> 0 | X77: 0 | BG77: =$N$77/3 -> 0 | BI77: =$N$77/3 -> 0 | BK77: =$N$77/3 -> 0 | BY77: =SUM(O77:BQ77) -> 0 | BZ77: =BY77-N77 -> 0
D78: =사업수지표!G57 -> 입주관리비 | N78: =사업수지표!AL57 -> 622050 | O78: =사업수지표!AR57 -> 0 | P78: =사업수지표!AR57 -> 0 | X78: 0 | BL78: =N78*50% -> 311025 | BM78: =N78*50% -> 311025 | BY78: =SUM(O78:BQ78) -> 622050 | BZ78: =BY78-N78 -> 0
D79: =사업수지표!G58 -> 예비비 | N79: =사업수지표!AL58 -> 9126625.9 | O79: =사업수지표!AR58 -> 0 | P79: =사업수지표!AR58 -> 0 | X79: 0 | AG79: 1200000 | AM79: 1200000 | AS79: 1200000 | AY79: 1200000 | BE79: 1200000 | BI79: 1200000 | BJ79: 600000 | BK79: 600000 | BL79: 726626 | BY79: =SUM(O79:BQ79) -> 9126626 | BZ79: =BY79-N79 -> 0.1425
D80: 소계 | N80: =SUM(N74:N79) -> 38978553 | O80: =SUM(O74:O79) -> 0 | P80: =SUM(P74:P79) -> 2737987.8 | Q80: =SUM(Q74:Q79) -> 0 | R80: =SUM(R74:R79) -> 0 | S80: =SUM(S74:S79) -> 0 | T80: =SUM(T74:T79) -> 0 | U80: =SUM(U74:U79) -> 0 | ... BY80: =SUM(BY74:BY79) -> 38978554 | BZ80: =BY80-N80 -> 0.14250001 | CA80: =SUM(P80:BX80)-BY80 -> 0
B81: 제세공과 | D81: =사업수지표!G60 -> 보존등기비 | N81: =사업수지표!AL60 -> 14896033 | O81: =사업수지표!AR60 -> 0 | P81: =사업수지표!AR60 -> 0 | X81: 0 | BL81: =N81 -> 14896033 | BN81: =O81 -> 0 | BY81: =SUM(O81:BQ81) -> 14896033 | BZ81: =BY81-N81 -> 0
D82: =사업수지표!G61 -> 상하수도분담금 | N82: =사업수지표!AL61 -> 1508000 | O82: =사업수지표!AR61 -> 0 | X82: 0 | AA82: =사업수지표!$AS$61 -> 0 | AY82: =N82/2 -> 754000 | BI82: =N82/2 -> 754000 | BY82: =SUM(O82:BQ82) -> 1508000 | BZ82: =BY82-N82 -> 0
D83: =사업수지표!G62 -> 토지분재산세 | N83: =사업수지표!AL62 -> 548685.27 | O83: =사업수지표!AR62 -> 0 | P83: =사업수지표!AR62 -> 0 | X83: 0 | AK83: =N83/3 -> 182895.09 | AW83: =N83/3 -> 182895.09 | BI83: =N83/3 -> 182895.09 | BY83: =SUM(O83:BQ83) -> 548685.27 | BZ83: =BY83-N83 -> 0
D84: =사업수지표!G63 -> 학교용지부담금 | N84: =사업수지표!AL63 -> 3472133.4 | O84: =사업수지표!AR63 -> 0 | P84: =사업수지표!AR63 -> 0 | X84: 0 | AH84: =N84 -> 3472133.4 | BL84: =$N$84*BK9 -> 0 | BM84: =$N$84*BL9 -> 0 | BN84: =$N$84*BM9 -> 0 | BO84: =$N$84*BM9 -> 0 | BP84: =$N$84*BP9 -> 0 | BQ84: =$N$84*BQ9 -> 0 | BR84: =$N$84*BQ9 -> 0 | BS84: =$N$84*BR9 -> 0 | BT84: =$N$84*BS9 -> 0 | BY84: =SUM(O84:BQ84) -> 3472133.4 | BZ84: =BY84-N84 -> 0
D85: =사업수지표!G64 -> 지방교육세 | N85: =사업수지표!AL64 -> 109737.05 | AH85: =N85 -> 109737.05 | BY85: =SUM(O85:BQ85) -> 109737.05
D86: =사업수지표!G65 -> 도시계획세 | N86: =사업수지표!AL65 -> 121930.06 | O86: =사업수지표!AR65 -> 0 | P86: =사업수지표!AR65 -> 0 | X86: 0 | AJ86: =N86 -> 121930.06 | BY86: =SUM(O86:BQ86) -> 121930.06 | BZ86: =BY86-N86 -> 0
D87: 소계 | N87: =SUM(N81:N86) -> 20656518 | O87: =SUM(O81:O86) -> 0 | P87: =SUM(P81:P86) -> 0 | Q87: =SUM(Q81:Q86) -> 0 | R87: =SUM(R81:R86) -> 0 | S87: =SUM(S81:S86) -> 0 | T87: =SUM(T81:T86) -> 0 | U87: =SUM(U81:U86) -> 0 | ... BY87: =SUM(BY81:BY86) -> 20656518 | BZ87: =BY87-N87 -> 0
D88: =사업수지표!G75 -> 신탁대지급금이자 | K88: =AK3 -> 0.0777 | N88: =BY88 -> 28436.963 | O88: =O132 -> 0 | P88: =P132 -> 0 | Q88: =Q132 -> 0 | R88: =R132 -> 0 | S88: =S132 -> 0 | T88: =T132 -> 0 | U88: =U132 -> 0 | V88: =V132 -> 0 | ... AA88: =AA132 -> 19962.206 | AH88: =AH132 -> 0 | AI88: =AI132 -> 0 | AJ88: =AJ132 -> 0 | AK88: =AK132 -> 0 | AL88: =AL132 -> 0 | AM88: =AM132 -> 0 | AN88: =AN132 -> 0 | AO88: =AO132 -> 0 | ... BP88: =BP132 -> 0 | BV88: =BV132 -> 0 | BW88: =BW132 -> 0 | BX88: =BX132 -> 0 | BY88: =SUM(O88:BQ88) -> 28436.963 | BZ88: =BY88-N88 -> 0
D89: =사업수지표!G76 -> 중도금대출이자 | K89: =AQ3 -> 0.042 | N89: =BY89 -> 21495221 | P89: =P143 -> 0 | X89: =X143 -> 0 | Y89: =Y143 -> 0 | Z89: =Z143 -> 0 | AA89: =AA143 -> 0 | AH89: =AH143 -> 0 | AI89: =AI143 -> 0 | AJ89: =AJ143 -> 0 | AK89: =AK143 -> 0 | AL89: =AL143 -> 51647.984 | AM89: =AM143 -> 60762.334 | AN89: =AN143 -> 306849.79 | AO89: =AO143 -> 331154.72 | ... BX89: =BX143 -> 0 | BY89: =SUM(O89:BQ89) -> 21495221 | BZ89: =BY89-N89 -> 0
D90: =사업수지표!G77 -> 중도금주선수수료 | K90: =사업수지표!BD77 -> 0.0015 | N90: =사업수지표!AL77 -> 863500 | P90: 0 | AL90: =N90 -> 863500 | BY90: =SUM(O90:BQ90) -> 863500
D91: =사업수지표!G78 -> PF부대비용 | N91: =사업수지표!AL78 -> 495000 | O91: =사업수지표!AR78 -> 0 | P91: =N91 -> 495000 | BY91: =SUM(O91:BQ91) -> 495000 | BZ91: =BY91-N91 -> 0
D92: =사업수지표!G79 -> 금융자문수수료 | K92: =사업수지표!BD79 -> 0 | N92: =사업수지표!AL79 -> 4950000 | P92: =N92 -> 4950000 | BY92: =SUM(O92:BQ92) -> 4950000 | BZ92: =BY92-N92 -> 0
D93: =사업수지표!G80 -> PF취급수수료 | K93: =사업수지표!BD80 -> 0 | N93: =사업수지표!AL80 -> 0 | P93: =사업수지표!AS80 -> 0 | BY93: =SUM(O93:BQ93) -> 0 | BZ93: =BY93-N93 -> 0
D94: =사업수지표!G81 -> PF이자 | G94: 일시 | K94: =사업수지표!BD81 -> 0.11 | N94: =BY94 -> 89918693 | BN94: ='IRR 계산'!H12 -> 89918693 | BQ94: =BQ112 -> 0 | BR94: =BR112 -> 0 | BS94: =BS112 -> 0 | BT94: =BT112 -> 0 | BU94: =BU112 -> 0 | BV94: =BV112 -> 0 | BW94: =BW112 -> 0 | BX94: =BX112 -> 0 | BY94: =SUM(O94:BQ94) -> 89918693 | BZ94: =BY94-N94 -> 0
G95: 한도 | K95: =사업수지표!BD82 -> 0.11 | N95: =BY95 -> 0 | P95: =사업수지표!AR81 -> 0 | X95: =X117 -> 0 | Y95: =Y117 -> 0 | Z95: =Z117 -> 0 | AA95: =AA117 -> 0 | AH95: =AH117 -> 0 | AI95: =AI117 -> 0 | AJ95: =AJ117 -> 0 | AK95: =AK117 -> 0 | AL95: =AL117 -> 0 | AM95: =AM117 -> 0 | AN95: =AN117 -> 0 | AO95: =AO117 -> 0 | ... BX95: =BX117 -> 0 | BY95: =SUM(O95:BQ95) -> 0 | BZ95: =BY95-N95 -> 0
D96: =사업수지표!G83 -> 0 | K96: =사업수지표!BC83 -> 0 | N96: =사업수지표!AL83 -> 0 | Y96: =N96 -> 0 | BY96: =SUM(P96:BL96) -> 0 | BZ96: =BY96-N96 -> 0
D97: =사업수지표!G84 -> 0 | N97: =사업수지표!AL84 -> 0 | Y97: =N97 -> 0 | BY97: =SUM(P97:BL97) -> 0 | BZ97: =BY97-N97 -> 0
D98: =사업수지표!G85 -> 0 | N98: =사업수지표!AL85 -> 0 | Y98: =N98 -> 0 | BY98: =SUM(P98:BL98) -> 0 | BZ98: =BY98-N98 -> 0
D99: =사업수지표!G86 -> 0 | N99: =사업수지표!AL86 -> 0 | Y99: =N99 -> 0 | BY99: =SUM(P99:BL99) -> 0 | BZ99: =BY99-N99 -> 0
D100: 소계 | N100: =SUM(N88:N99) -> 1.1775085e+08 | O100: =SUM(O88:O99) -> 0 | P100: =SUM(P88:P99) -> 5445000 | Q100: =SUM(Q88:Q99) -> 0 | R100: =SUM(R88:R99) -> 0 | S100: =SUM(S88:S99) -> 0 | T100: =SUM(T88:T99) -> 0 | U100: =SUM(U88:U99) -> 0 | ... BY100: =SUM(BY88:BY99) -> 1.1775085e+08 | BZ100: =BY100-N100 -> 0 | CA100: =SUM(O100:BX100)-BY100 -> 0
...

Sheet Exit 분양률
B1: 경기도 화성시 장짐리 공동주택 신축사업 Exit 분양률
B4: [총 분양수입금] | F4: (단위 : 천원) | H4: [잔금 비율]
B5: 구 분 | C5: 공동주택 | D5: 발코니확장비 | E5: 근린생활시설 | F5: 매출 합계 | H5: 공동주택 | I5: 발코니확장비 | J5: 근린생활시설
B6: 금액 | C6: =사업수지표!Z18 -> 8.6803334e+08 | D6: =사업수지표!Z22 -> 37700000 | E6: =사업수지표!Z21 -> 6929246.5 | F6: =C6+D6+E6 -> 9.1266259e+08 | H6: 0.3 | I6: 1 | J6: 0.5
B7: 누계액 | C7: =C6 -> 8.6803334e+08 | D7: =C7+D6 -> 9.0573334e+08 | E7: =D7+E6 -> 9.1266259e+08 | F7: =E7=F6 -> TRUE
B10: [분양수입금 잔금] | F10: (단위 : 천원)
B11: 구 분 | C11: 공동주택 | D11: 발코니확장비 | E11: 근린생활시설 | F11: 잔금 합계
B12: 금액 | C12: =C6*H6 -> 2.6041e+08 | D12: =D6*I6 -> 37700000 | E12: =E6*J6 -> 3464623.2 | F12: =C12+D12+E12 -> 3.0157463e+08
B13: 누계액 | C13: =C12 -> 2.6041e+08 | D13: =C13+D12 -> 2.9811e+08 | E13: =E12+D13 -> 3.0157463e+08 | F13: =E13=F12 -> TRUE
E15: =C13+E12 -> 2.6387463e+08
B16: [공동주택, 발코니확장비, 근린생활시설 분양수입금(잔금) 기준] | F16: (단위 : 천원)
B17: 잔금납입률 | C17: 대출금상환 | D17: 대출금잔액 | E17: LTV | F17: 비 고
B18: 0 | D18: =사업수지표!AW81 -> 149000000 | E18: =IF(($D$18-C18)/($E$13*(1-B18))>0,($D$18-C18)/($E$13*(1-B18)),0) -> 0.4940734
B19: 0.1 | C19: =$E$13*B19 -> 30157463 | D19: =IF($D$18-C19>0,$D$18-C19,0) -> 1.1884254e+08 | E19: =IF(($D$18-C19)/($E$13*(1-B19))>0,($D$18-C19)/($E$13*(1-B19)),0) -> 0.43785933
B20: 0.2 | C20: =$E$13*B20 -> 60314925 | D20: =IF($D$18-C20>0,$D$18-C20,0) -> 88685075 | E20: =IF(($D$18-C20)/($E$13*(1-B20))>0,($D$18-C20)/($E$13*(1-B20)),0) -> 0.36759175
B21: 0.3 | C21: =$E$13*B21 -> 90472388 | D21: =IF($D$18-C21>0,$D$18-C21,0) -> 58527612 | E21: =IF(($D$18-C21)/($E$13*(1-B21))>0,($D$18-C21)/($E$13*(1-B21)),0) -> 0.27724771
B22: 0.4 | C22: =$E$13*B22 -> 1.2062985e+08 | D22: =IF($D$18-C22>0,$D$18-C22,0) -> 28370150 | E22: =IF(($D$18-C22)/($E$13*(1-B22))>0,($D$18-C22)/($E$13*(1-B22)),0) -> 0.156789
B23: 0.4940734 | C23: =$E$13*B23 -> 1.49e+08 | D23: =IF($D$18-C23<0,0,$D$18-C23) -> 5.9604645e-08 | E23: =IF(($D$18-C23)/($E$13*(1-B23))>0,($D$18-C23)/($E$13*(1-B23)),0) -> 3.9065896e-16
B24: 0.5 | C24: =$E$13*B24 -> 1.5078731e+08 | E24: =IF(($D$18-C24)/($E$13*(1-B24))>0,($D$18-C24)/($E$13*(1-B24)),0) -> 0
B27: [공동주택, 근생 분양수입금(잔금) 기준] | F27: (단위 : 천원)
B28: 잔금납입률 | C28: 대출금상환 | D28: 대출금잔액 | E28: LTV | F28: 비 고
B29: 0 | C29: =D13*B29 -> 0 | D29: =D18 -> 149000000 | E29: =IF(($D$29-C29)/(E15*(1-B29))>0,($D$29-C29)/(E15*(1-B29)),0) -> 0.5646621
B30: 0.1 | C30: =E15*B30 -> 26387463 | D30: =IF($D$29-C30>0,$D$29-C30,0) -> 1.2261254e+08 | E30: =IF(($D$29-C30)/(E15*(1-B30))>0,($D$29-C30)/(E15*(1-B30)),0) -> 0.51629122
B31: 0.2 | C31: =E15*B31 -> 52774925 | D31: =IF($D$29-C31>0,$D$29-C31,0) -> 96225075 | E31: =IF(($D$29-C31)/(E15*(1-B31))>0,($D$29-C31)/(E15*(1-B31)),0) -> 0.45582763
B32: 0.3 | C32: =E15*B32 -> 79162388 | D32: =IF($D$29-C32>0,$D$29-C32,0) -> 69837612 | E32: =IF(($D$29-C32)/(E15*(1-B32))>0,($D$29-C32)/(E15*(1-B32)),0) -> 0.37808871
B33: 0.4 | C33: =E15*B33 -> 1.0554985e+08 | D33: =IF($D$29-C33>0,$D$29-C33,0) -> 43450150 | E33: =IF(($D$29-C33)/(E15*(1-B33))>0,($D$29-C33)/(E15*(1-B33)),0) -> 0.27443683
B34: 0.5 | C34: =E15*B34 -> 1.3193731e+08 | D34: =IF($D$29-C34>0,$D$29-C34,0) -> 17062687 | E34: =IF(($D$29-C34)/(E15*(1-B34))>0,($D$29-C34)/(E15*(1-B34)),0) -> 0.1293242
B35: 0.5646621 | C35: =E15*B35 -> 1.49e+08 | D35: =IF($D$29-C35>0,$D$29-C35,0) -> 5.9604645e-08 | E35: =IF(($D$29-C35)/(E15*(1-B35))>0,($D$29-C35)/(E15*(1-B35)),0) -> 5.1886694e-16
B37: [공동주택, 발코니확장비(잔금) 기준] | F37: (단위 : 천원)
B38: 잔금납입률 | C38: 대출금상환 | D38: 대출금잔액 | E38: LTV | F38: 비 고
B39: 0 | D39: 149000000 | E39: =IF(($D$18-C39)/(D13*(1-B39))>0,($D$18-C39)/(D13*(1-B39)),0) -> 0.4998155
B40: 0.1 | C40: =D13*B40 -> 29811000 | D40: =IF($D$18-C40>0,$D$18-C40,0) -> 1.19189e+08 | E40: =IF(($D$18-C40)/(D13*(1-B40))>0,($D$18-C40)/(D13*(1-B40)),0) -> 0.44423945
B41: 0.2 | C41: =D13*B41 -> 59622000 | D41: =IF($D$18-C41>0,$D$18-C41,0) -> 89378000 | E41: =IF(($D$18-C41)/(D13*(1-B41))>0,($D$18-C41)/(D13*(1-B41)),0) -> 0.37476938
B42: 0.3 | C42: =D13*B42 -> 89433001 | D42: =IF($D$18-C42>0,$D$18-C42,0) -> 59566999 | E42: =IF(($D$18-C42)/(D13*(1-B42))>0,($D$18-C42)/(D13*(1-B42)),0) -> 0.28545072
B43: 0.4 | C43: =D13*B43 -> 1.19244e+08 | D43: =IF($D$18-C43>0,$D$18-C43,0) -> 29755999 | E43: =IF(($D$18-C43)/(D13*(1-B43))>0,($D$18-C43)/(D13*(1-B43)),0) -> 0.16635917
B44: 0.4998155 | C44: =D13*B44 -> 149000000 | D44: =IF($D$18-C44<0,0,$D$18-C44) -> 0 | E44: =IF(($D$18-C44)/($E$13*(1-B44))>0,($D$18-C44)/($E$13*(1-B44)),0) -> 0

Sheet 자금판-HF
B1: PF 자금판
F2: 대출기간 | H2: 41
B3: IN | E3: OUT
B4: PF | C4: Tr.A | D4: 22000000000 | E4: 브릿지상환 (170억원) | F4: 중랑신협 | H4: 10000000000
C5: Tr.B | D5: 1500000000 | F5: 바로저축 | H5: 4000000000 | K5: 상환 | L5: 대출잔액 | M5: 비고
B6: 추가에쿼티 | F6: LK | J6: 기표 | L6: =SUM(D4:D5) -> 23500000000
F7: 웨이브 | H7: 3000000000 | J7: +4M | L7: =L6-K7 -> 23500000000
E8: PF비용예치 | F8: 금융예비비 | H8: 30000000
F9: HF수수료(0.5%) | H9: =현금흐름표!#REF!*1000 -> #REF!
F10: 금융주관(1%) | H10: =SUM(D4:D5)*1% -> 235000000
F11: PF 취급수수료 | G11: Tr.A (2.0%) | H11: =D4*2% -> 440000000
G12: Tr.B (17.9%) | H12: =D5*17.9% -> 268500000
E13: PF이자 | F13: 현금흐름표상 PF이자
F14: 41 | G14: Tr.A (6.5%) | H14: =D4*6.5%/12*F14 -> 4.8858333e+09
G15: Tr.B (8.0%) | H15: =D5*8%/12*F14 -> 410000000
F16: 이자합계 | H16: =SUM(H14:H15) -> 5.2958333e+09
B17: 계 | D17: =SUM(D4:D16) -> 23500000000 | E17: 계 | H17: =SUM(H4:H12)+H13+H16 -> #REF!

Sheet 할인분양 계산
B2: ■ 할인분양 적용
B4: 공동주택 수입 | C4: =SUM(사업수지표!#REF!,사업수지표!#REF!) -> #REF!
B5: 상가 수입 | C5: =사업수지표!#REF! -> #REF!
B6: 필요사업비 | C6: =사업수지표!AT89 -> 4.8990429e+08
B7: 84A | C7: =사업수지표!#REF! -> #REF! | D7: =C7*0.8 -> #REF!
B8: 84B | C8: =사업수지표!#REF! -> #REF! | D8: =C8*0.8 -> #REF!
B9: 107 | C9: =사업수지표!#REF! -> #REF! | D9: =C9*0.8 -> #REF!
B11: 분양대금 | D11: 부족사업비 | E11: 미분양액 | F11: 미분양할인율 | G11: 84A | H11: 84B | I11: 107
B12: 0.5 | C12: =$C$4*B12 -> #REF! | D12: =$C$6-C12 -> #REF! | E12: =SUM($C$4:$C$5)-C12 -> #REF! | F12: =1-D12/E12 -> #REF! | G12: =$C$7*(1-F12) -> #REF! | H12: =$C$8*(1-F12) -> #REF! | I12: =$C$9*(1-F12) -> #REF!
B13: 0.4 | C13: =$C$4*B13 -> #REF! | D13: =$C$6-C13 -> #REF! | E13: =SUM($C$4:$C$5)-C13 -> #REF! | F13: =1-D13/E13 -> #REF! | G13: =$C$7*(1-F13) -> #REF! | H13: =$C$8*(1-F13) -> #REF! | I13: =$C$9*(1-F13) -> #REF!
B14: 0.3 | C14: =$C$4*B14 -> #REF! | D14: =$C$6-C14 -> #REF! | E14: =SUM($C$4:$C$5)-C14 -> #REF! | F14: =1-D14/E14 -> #REF! | G14: =$C$7*(1-F14) -> #REF! | H14: =$C$8*(1-F14) -> #REF! | I14: =$C$9*(1-F14) -> #REF!
B15: 0.2 | C15: =$C$4*B15 -> #REF! | D15: =$C$6-C15 -> #REF! | E15: =SUM($C$4:$C$5)-C15 -> #REF! | F15: =1-D15/E15 -> #REF! | G15: =$C$7*(1-F15) -> #REF! | H15: =$C$8*(1-F15) -> #REF! | I15: =$C$9*(1-F15) -> #REF!
B16: 0.1 | C16: =$C$4*B16 -> #REF! | D16: =$C$6-C16 -> #REF! | E16: =SUM($C$4:$C$5)-C16 -> #REF! | F16: =1-D16/E16 -> #REF! | G16: =$C$7*(1-F16) -> #REF! | H16: =$C$8*(1-F16) -> #REF! | I16: =$C$9*(1-F16) -> #REF!
B17: 0.09 | C17: =$C$4*B17 -> #REF! | D17: =$C$6-C17 -> #REF! | E17: =SUM($C$4:$C$5)-C17 -> #REF! | F17: =1-D17/E17 -> #REF! | G17: =$C$7*(1-F17) -> #REF! | H17: =$C$8*(1-F17) -> #REF! | I17: =$C$9*(1-F17) -> #REF!
B18: 0.05 | C18: =$C$4*B18 -> #REF! | D18: =$C$6-C18 -> #REF! | E18: =SUM($C$4:$C$5)-C18 -> #REF! | F18: =1-D18/E18 -> #REF! | G18: =$C$7*(1-F18) -> #REF! | H18: =$C$8*(1-F18) -> #REF! | I18: =$C$9*(1-F18) -> #REF!
C20: 238065 | D20: 0.378 | E20: =C20/(1-D20) -> 382741.16 | F20: =E20*0.8 -> 306192.93
C21: 265300 | D21: 0.307 | E21: =C21/(1-D21) -> 382828.28
C22: 267560 | D22: 0.301 | E22: =C22/(1-D22) -> 382775.39

Sheet IRR 계산
A1: PF대출기간 | C1: IRR | G1: *단위 : 억원
A2: 50 | B2: 개월 | C2: 0.11 | H2: 준공시점 상환
C3: 개월 | D3: 12 | E3: 12 | F3: 12 | G3: 12 | H3: 2
C4: 연 | D4: 1 | E4: 2 | F4: 3 | G4: 4 | H4: 4.1666667
B6: 대출금액(원금) | C6: 149000000
B7: 이자 | D7: =$C$6*$C$2 -> 16390000 | E7: =$C$6*$C$2 -> 16390000 | F7: =$C$6*$C$2 -> 16390000 | G7: =$C$6*$C$2 -> 16390000 | H7: =C6*C2*(2/12) -> 2731666.7
H8: =G7*(1+$C$2)^(D4+($H$3/12)) -> 18512103
H9: =F7*(1+$C$2)^(E4+($H$3/12)) -> 20548435
H10: =E7*(1+$C$2)^(F4+($H$3/12)) -> 22808762
H11: =D7*(1+$C$2)^(G4+($H$3/12)) -> 25317726
G12: 총 이자금액(천원) | H12: =SUM(H7:H11) -> 89918693

Sheet 공정률
B1: ▣ 공정률
C2: 구분 | F2: =현금흐름표!AA6 -> 46419 | G2: =현금흐름표!AB6 -> 46447 | H2: =현금흐름표!AC6 -> 46478 | I2: =현금흐름표!AD6 -> 46508 | J2: =현금흐름표!AE6 -> 46539 | K2: =현금흐름표!AF6 -> 46569 | L2: =현금흐름표!AG6 -> 46600 | M2: =현금흐름표!AH6 -> 46631 | ... BA2: =현금흐름표!BV6 -> 47423
C3: 공사진행스케줄 | F3: 1 | G3: =F3+1 -> 2 | H3: =G3+1 -> 3 | I3: =H3+1 -> 4 | J3: =I3+1 -> 5 | K3: =J3+1 -> 6 | L3: =K3+1 -> 7 | M3: =L3+1 -> 8 | N3: =M3+1 -> 9 | ... BA3: =AZ3+1 -> 48
C4: 주상복합 | D4: 공정률 | E4: =SUM(F4:BA4) -> 1 | F4: =VLOOKUP($E$5,$C8:$AZ41,F3+2) -> 0.0096 | G4: =VLOOKUP($E$5,$C8:$AZ41,G3+2) -> 0.0096 | H4: =VLOOKUP($E$5,$C8:$AZ41,H3+2) -> 0.0116 | I4: =VLOOKUP($E$5,$C8:$AZ41,I3+2) -> 0.0116 | J4: =VLOOKUP($E$5,$C8:$AZ41,J3+2) -> 0.0136 | K4: =VLOOKUP($E$5,$C8:$AZ41,K3+2) -> 0.0136 | L4: =VLOOKUP($E$5,$C8:$AZ41,L3+2) -> 0.0186 | M4: =VLOOKUP($E$5,$C8:$AZ41,M3+2) -> 0.0186 | ... BA4: =VLOOKUP($E$5,$C8:$AZ41,BA3+2) -> 0
D5: 누계공정률 | E5: 37 | F5: =F4 -> 0.0096 | G5: =F5+G4 -> 0.0192 | H5: =G5+H4 -> 0.0308 | I5: =H5+I4 -> 0.0424 | J5: =I5+J4 -> 0.056 | K5: =J5+K4 -> 0.0696 | L5: =K5+L4 -> 0.0882 | M5: =L5+M4 -> 0.1068 | N5: =M5+N4 -> 0.1284 | ... BA5: =AZ5+BA4 -> 1
C7: ※ 공정률 Table
C8: 15 | D8: 개월 | E8: 0.049 | F8: 0.049 | G8: 0.053 | H8: 0.053 | I8: 0.057 | J8: 0.057 | K8: 0.066 | L8: 0.066 | M8: 0.073 | N8: 0.073 | O8: 0.078 | P8: 0.078 | Q8: 0.083 | R8: 0.083 | S8: 0.082 | BA8: 1
C9: 16 | D9: 개월 | E9: 0.043 | F9: 0.043 | G9: 0.047 | H9: 0.047 | I9: 0.051 | J9: 0.051 | K9: 0.06 | L9: 0.06 | M9: 0.067 | N9: 0.067 | O9: 0.072 | P9: 0.072 | Q9: 0.077 | R9: 0.077 | S9: 0.085 | T9: 0.081 | BA9: 1
C10: 17 | D10: 개월 | E10: 0.038 | F10: 0.038 | G10: 0.042 | H10: 0.042 | I10: 0.046 | J10: 0.046 | K10: 0.055 | L10: 0.055 | M10: 0.062 | N10: 0.062 | O10: 0.067 | P10: 0.067 | Q10: 0.072 | R10: 0.072 | S10: 0.08 | T10: 0.08 | U10: 0.076 | BA10: 1
C11: 18 | D11: 개월 | E11: 0.0335 | F11: 0.0335 | G11: 0.0375 | H11: 0.0375 | I11: 0.0415 | J11: 0.0415 | K11: 0.0505 | L11: 0.0505 | M11: 0.0575 | N11: 0.0575 | O11: 0.0625 | P11: 0.0625 | Q11: 0.0675 | R11: 0.0675 | S11: 0.0755 | T11: 0.0755 | U11: 0.0755 | V11: 0.0725 | BA11: 1
C12: 19 | D12: 개월 | E12: 0.0295 | F12: 0.0295 | G12: 0.0335 | H12: 0.0335 | I12: 0.0375 | J12: 0.0375 | K12: 0.0465 | L12: 0.0465 | M12: 0.0535 | N12: 0.0535 | O12: 0.0585 | P12: 0.0585 | Q12: 0.0635 | R12: 0.0635 | S12: 0.0715 | T12: 0.0715 | U12: 0.0715 | V12: 0.0715 | W12: 0.069 | BA12: 1
C13: 20 | D13: 개월 | E13: 0.0263 | F13: 0.0263 | G13: 0.0303 | H13: 0.0303 | I13: 0.0343 | J13: 0.0343 | K13: 0.0433 | L13: 0.0433 | M13: 0.0503 | N13: 0.0503 | O13: 0.0553 | P13: 0.0553 | Q13: 0.0603 | R13: 0.0603 | S13: 0.0683 | T13: 0.0683 | U13: 0.0683 | V13: 0.0683 | W13: 0.0683 | X13: 0.0583 | BA13: 1
C14: 21 | D14: 개월 | E14: 0.0228 | F14: 0.0228 | G14: 0.0268 | H14: 0.0268 | I14: 0.0308 | J14: 0.0308 | K14: 0.0398 | L14: 0.0398 | M14: 0.0468 | N14: 0.0468 | O14: 0.0518 | P14: 0.0518 | Q14: 0.0568 | R14: 0.0568 | S14: 0.0648 | T14: 0.0648 | U14: 0.0648 | V14: 0.0648 | W14: 0.0648 | X14: 0.0648 | Y14: 0.06 | BA14: 1
C15: 22 | D15: 개월 | E15: 0.0203 | F15: 0.0203 | G15: 0.0243 | H15: 0.0243 | I15: 0.0283 | J15: 0.0283 | K15: 0.0373 | L15: 0.0373 | M15: 0.0443 | N15: 0.0443 | O15: 0.0493 | P15: 0.0493 | Q15: 0.0543 | R15: 0.0543 | S15: 0.0623 | T15: 0.0623 | U15: 0.0623 | V15: 0.0623 | W15: 0.0623 | X15: 0.0623 | Y15: 0.0573 | Z15: 0.0527 | BA15: 1
C16: 23 | D16: 개월 | E16: 0.0178 | F16: 0.0178 | G16: 0.0218 | H16: 0.0218 | I16: 0.0258 | J16: 0.0258 | K16: 0.0348 | L16: 0.0348 | M16: 0.0418 | N16: 0.0418 | O16: 0.0468 | P16: 0.0468 | Q16: 0.0518 | R16: 0.0518 | S16: 0.0598 | T16: 0.0598 | U16: 0.0598 | V16: 0.0598 | W16: 0.0598 | X16: 0.0598 | Y16: 0.0548 | Z16: 0.0548 | AA16: 0.0504 | BA16: 1
C17: 24 | D17: 개월 | E17: 0.0158 | F17: 0.0158 | G17: 0.0198 | H17: 0.0198 | I17: 0.0238 | J17: 0.0238 | K17: 0.0328 | L17: 0.0328 | M17: 0.0398 | N17: 0.0398 | O17: 0.0448 | P17: 0.0448 | Q17: 0.0498 | R17: 0.0498 | S17: 0.0578 | T17: 0.0578 | U17: 0.0578 | V17: 0.0578 | W17: 0.0578 | X17: 0.0578 | Y17: 0.0528 | Z17: 0.0528 | AA17: 0.0478 | AB17: 0.0466 | BA17: 1
C18: 25 | D18: 개월 | E18: 0.014 | F18: 0.014 | G18: 0.018 | H18: 0.018 | I18: 0.022 | J18: 0.022 | K18: 0.031 | L18: 0.031 | M18: 0.038 | N18: 0.038 | O18: 0.043 | P18: 0.043 | Q18: 0.048 | R18: 0.048 | S18: 0.056 | T18: 0.056 | U18: 0.056 | V18: 0.056 | W18: 0.056 | X18: 0.056 | Y18: 0.051 | Z18: 0.051 | AA18: 0.046 | AB18: 0.046 | AC18: 0.042 | BA18: 1
C19: 26 | D19: 개월 | E19: 0.0125 | F19: 0.0125 | G19: 0.0165 | H19: 0.0165 | I19: 0.0205 | J19: 0.0205 | K19: 0.0295 | L19: 0.0295 | M19: 0.0365 | N19: 0.0365 | O19: 0.0415 | P19: 0.0415 | Q19: 0.0465 | R19: 0.0465 | S19: 0.0545 | T19: 0.0545 | U19: 0.0545 | V19: 0.0545 | W19: 0.0545 | X19: 0.0545 | Y19: 0.0495 | Z19: 0.0495 | AA19: 0.0445 | AB19: 0.0445 | AC19: 0.0395 | AD19: 0.0385 | BA19: 1
C20: 27 | D20: 개월 | E20: 0.011 | F20: 0.011 | G20: 0.015 | H20: 0.015 | I20: 0.019 | J20: 0.019 | K20: 0.028 | L20: 0.028 | M20: 0.035 | N20: 0.035 | O20: 0.04 | P20: 0.04 | Q20: 0.045 | R20: 0.045 | S20: 0.053 | T20: 0.053 | U20: 0.053 | V20: 0.053 | W20: 0.053 | X20: 0.053 | Y20: 0.048 | Z20: 0.048 | AA20: 0.043 | AB20: 0.043 | AC20: 0.038 | AD20: 0.038 | AE20: 0.038 | BA20: 1
C21: 28 | D21: 개월 | E21: 0.0099 | F21: 0.0099 | G21: 0.0139 | H21: 0.0139 | I21: 0.0179 | J21: 0.0179 | K21: 0.0269 | L21: 0.0269 | M21: 0.0339 | N21: 0.0339 | O21: 0.0389 | P21: 0.0389 | Q21: 0.0439 | R21: 0.0439 | S21: 0.0519 | T21: 0.0519 | U21: 0.0519 | V21: 0.0519 | W21: 0.0519 | X21: 0.0519 | Y21: 0.0469 | Z21: 0.0469 | AA21: 0.0419 | AB21: 0.0419 | AC21: 0.0369 | AD21: 0.0369 | AE21: 0.0339 | AF21: 0.0327 | BA21: 1
C22: 29 | D22: 개월 | E22: 0.0088 | F22: 0.0088 | G22: 0.0128 | H22: 0.0128 | I22: 0.0168 | J22: 0.0168 | K22: 0.0258 | L22: 0.0258 | M22: 0.0328 | N22: 0.0328 | O22: 0.0378 | P22: 0.0378 | Q22: 0.0428 | R22: 0.0428 | S22: 0.0508 | T22: 0.0508 | U22: 0.0508 | V22: 0.0508 | W22: 0.0508 | X22: 0.0508 | Y22: 0.0458 | Z22: 0.0458 | AA22: 0.0408 | AB22: 0.0408 | AC22: 0.0358 | AD22: 0.0358 | AE22: 0.0328 | AF22: 0.0328 | AG22: 0.0296 | BA22: 1
C23: 30 | D23: 개월 | E23: 0.008 | F23: 0.008 | G23: 0.012 | H23: 0.012 | I23: 0.016 | J23: 0.016 | K23: 0.025 | L23: 0.025 | M23: 0.032 | N23: 0.032 | O23: 0.037 | P23: 0.037 | Q23: 0.042 | R23: 0.042 | S23: 0.05 | T23: 0.05 | U23: 0.05 | V23: 0.05 | W23: 0.05 | X23: 0.05 | Y23: 0.045 | Z23: 0.045 | AA23: 0.04 | AB23: 0.04 | AC23: 0.035 | AD23: 0.035 | AE23: 0.032 | AF23: 0.032 | AG23: 0.03 | AH23: 0.022 | BA23: 1
C24: 31 | D24: 개월 | E24: 0.0164 | F24: 0.0164 | G24: 0.0184 | H24: 0.0184 | I24: 0.0204 | J24: 0.0204 | K24: 0.0254 | L24: 0.0254 | M24: 0.0284 | N24: 0.0284 | O24: 0.0314 | P24: 0.0314 | Q24: 0.0334 | R24: 0.0334 | S24: 0.0354 | T24: 0.0354 | U24: 0.0354 | V24: 0.0354 | W24: 0.0354 | X24: 0.0354 | Y24: 0.0374 | Z24: 0.0374 | AA24: 0.0374 | AB24: 0.0374 | AC24: 0.0394 | AD24: 0.0394 | AE24: 0.0414 | AF24: 0.0414 | AG24: 0.0434 | AH24: 0.0434 | AI24: 0.042 | BA24: 1
C25: 32 | D25: 개월 | E25: 0.015 | F25: 0.015 | G25: 0.017 | H25: 0.017 | I25: 0.019 | J25: 0.019 | K25: 0.024 | L25: 0.024 | M25: 0.027 | N25: 0.027 | O25: 0.03 | P25: 0.03 | Q25: 0.032 | R25: 0.032 | S25: 0.034 | T25: 0.034 | U25: 0.034 | V25: 0.034 | W25: 0.034 | X25: 0.034 | Y25: 0.036 | Z25: 0.036 | AA25: 0.036 | AB25: 0.036 | AC25: 0.038 | AD25: 0.038 | AE25: 0.04 | AF25: 0.04 | AG25: 0.042 | AH25: 0.042 | AI25: 0.042 | AJ25: 0.042 | BA25: 1
C26: 33 | D26: 개월 | E26: 0.0139 | F26: 0.0139 | G26: 0.0159 | H26: 0.0159 | I26: 0.0179 | J26: 0.0179 | K26: 0.0229 | L26: 0.0229 | M26: 0.0259 | N26: 0.0259 | O26: 0.0289 | P26: 0.0289 | Q26: 0.0309 | R26: 0.0309 | S26: 0.0329 | T26: 0.0329 | U26: 0.0329 | V26: 0.0329 | W26: 0.0329 | X26: 0.0329 | Y26: 0.0349 | Z26: 0.0349 | AA26: 0.0349 | AB26: 0.0349 | AC26: 0.0369 | AD26: 0.0369 | AE26: 0.0389 | AF26: 0.0389 | AG26: 0.0409 | AH26: 0.0409 | AI26: 0.0409 | AJ26: 0.0409 | AK26: 0.0352 | BA26: 1
C27: 34 | D27: 개월 | E27: 0.0129 | F27: 0.0129 | G27: 0.0149 | H27: 0.0149 | I27: 0.0169 | J27: 0.0169 | K27: 0.0219 | L27: 0.0219 | M27: 0.0249 | N27: 0.0249 | O27: 0.0279 | P27: 0.0279 | Q27: 0.0299 | R27: 0.0299 | S27: 0.0319 | T27: 0.0319 | U27: 0.0319 | V27: 0.0319 | W27: 0.0319 | X27: 0.0319 | Y27: 0.0339 | Z27: 0.0339 | AA27: 0.0339 | AB27: 0.0339 | AC27: 0.0359 | AD27: 0.0359 | AE27: 0.0379 | AF27: 0.0379 | AG27: 0.0399 | AH27: 0.0399 | AI27: 0.0399 | AJ27: 0.0399 | AK27: 0.0379 | AL27: 0.0293 | BA27: 1
C28: 35 | D28: 개월 | E28: 0.0117 | F28: 0.0117 | G28: 0.0137 | H28: 0.0137 | I28: 0.0157 | J28: 0.0157 | K28: 0.0207 | L28: 0.0207 | M28: 0.0237 | N28: 0.0237 | O28: 0.0267 | P28: 0.0267 | Q28: 0.0287 | R28: 0.0287 | S28: 0.0307 | T28: 0.0307 | U28: 0.0307 | V28: 0.0307 | W28: 0.0307 | X28: 0.0307 | Y28: 0.0327 | Z28: 0.0327 | AA28: 0.0327 | AB28: 0.0327 | AC28: 0.0347 | AD28: 0.0347 | AE28: 0.0367 | AF28: 0.0367 | AG28: 0.0387 | AH28: 0.0387 | AI28: 0.0387 | AJ28: 0.0387 | AK28: 0.0367 | AL28: 0.0367 | AM28: 0.0322 | BA28: 1
C29: 36 | D29: 개월 | E29: 0.0105 | F29: 0.0105 | G29: 0.0125 | H29: 0.0125 | I29: 0.0145 | J29: 0.0145 | K29: 0.0195 | L29: 0.0195 | M29: 0.0225 | N29: 0.0225 | O29: 0.0255 | P29: 0.0255 | Q29: 0.0275 | R29: 0.0275 | S29: 0.0295 | T29: 0.0295 | U29: 0.0295 | V29: 0.0295 | W29: 0.0295 | X29: 0.0295 | Y29: 0.0315 | Z29: 0.0315 | AA29: 0.0315 | AB29: 0.0315 | AC29: 0.0335 | AD29: 0.0335 | AE29: 0.0355 | AF29: 0.0355 | AG29: 0.0375 | AH29: 0.0375 | AI29: 0.0375 | AJ29: 0.0375 | AK29: 0.0355 | AL29: 0.0355 | AM29: 0.0355 | AN29: 0.0375 | BA29: 1
C30: 37 | D30: 개월 | E30: 0.0096 | F30: 0.0096 | G30: 0.0116 | H30: 0.0116 | I30: 0.0136 | J30: 0.0136 | K30: 0.0186 | L30: 0.0186 | M30: 0.0216 | N30: 0.0216 | O30: 0.0246 | P30: 0.0246 | Q30: 0.0266 | R30: 0.0266 | S30: 0.0286 | T30: 0.0286 | U30: 0.0286 | V30: 0.0286 | W30: 0.0286 | X30: 0.0286 | Y30: 0.0306 | Z30: 0.0306 | AA30: 0.0306 | AB30: 0.0306 | AC30: 0.0326 | AD30: 0.0326 | AE30: 0.0346 | AF30: 0.0346 | AG30: 0.0366 | AH30: 0.0366 | AI30: 0.0366 | AJ30: 0.0366 | AK30: 0.0346 | AL30: 0.0346 | AM30: 0.0346 | AN30: 0.0346 | AO30: 0.0344 | BA30: 1
C31: 38 | D31: 개월 | E31: 0.0088 | F31: 0.0088 | G31: 0.0108 | H31: 0.0108 | I31: 0.0128 | J31: 0.0128 | K31: 0.0178 | L31: 0.0178 | M31: 0.0208 | N31: 0.0208 | O31: 0.0238 | P31: 0.0238 | Q31: 0.0258 | R31: 0.0258 | S31: 0.0278 | T31: 0.0278 | U31: 0.0278 | V31: 0.0278 | W31: 0.0278 | X31: 0.0278 | Y31: 0.0298 | Z31: 0.0298 | AA31: 0.0298 | AB31: 0.0298 | AC31: 0.0318 | AD31: 0.0318 | AE31: 0.0338 | AF31: 0.0338 | AG31: 0.0358 | AH31: 0.0358 | AI31: 0.0358 | AJ31: 0.0358 | AK31: 0.0338 | AL31: 0.0338 | AM31: 0.0338 | AN31: 0.0338 | AO31: 0.0318 | AP31: 0.0314 | BA31: 1
C32: 39 | D32: 개월 | E32: 0.008 | F32: 0.008 | G32: 0.01 | H32: 0.01 | I32: 0.012 | J32: 0.012 | K32: 0.017 | L32: 0.017 | M32: 0.02 | N32: 0.02 | O32: 0.023 | P32: 0.023 | Q32: 0.025 | R32: 0.025 | S32: 0.027 | T32: 0.027 | U32: 0.027 | V32: 0.027 | W32: 0.027 | X32: 0.027 | Y32: 0.029 | Z32: 0.029 | AA32: 0.029 | AB32: 0.029 | AC32: 0.031 | AD32: 0.031 | AE32: 0.033 | AF32: 0.033 | AG32: 0.035 | AH32: 0.035 | AI32: 0.035 | AJ32: 0.035 | AK32: 0.033 | AL32: 0.033 | AM32: 0.033 | AN32: 0.033 | AO32: 0.031 | AP32: 0.031 | AQ32: 0.03 | BA32: 1
C33: 40 | D33: 개월 | E33: 0.00735 | F33: 0.00735 | G33: 0.00935 | H33: 0.00935 | I33: 0.01135 | J33: 0.01135 | K33: 0.01635 | L33: 0.01635 | M33: 0.01935 | N33: 0.01935 | O33: 0.02235 | P33: 0.02235 | Q33: 0.02435 | R33: 0.02435 | S33: 0.02635 | T33: 0.02635 | U33: 0.02635 | V33: 0.02635 | W33: 0.02635 | X33: 0.02635 | Y33: 0.02835 | Z33: 0.02835 | AA33: 0.02835 | AB33: 0.02835 | AC33: 0.03035 | AD33: 0.03035 | AE33: 0.03235 | AF33: 0.03235 | AG33: 0.03435 | AH33: 0.03435 | AI33: 0.03435 | AJ33: 0.03435 | AK33: 0.03235 | AL33: 0.03235 | AM33: 0.03235 | AN33: 0.03235 | AO33: 0.03035 | AP33: 0.03035 | AQ33: 0.02735 | AR33: 0.02735 | BA33: 1
C34: 41 | D34: 개월 | E34: 0.0067 | F34: 0.0067 | G34: 0.0087 | H34: 0.0087 | I34: 0.0107 | J34: 0.0107 | K34: 0.0157 | L34: 0.0157 | M34: 0.0187 | N34: 0.0187 | O34: 0.0217 | P34: 0.0217 | Q34: 0.0237 | R34: 0.0237 | S34: 0.0257 | T34: 0.0257 | U34: 0.0257 | V34: 0.0257 | W34: 0.0257 | X34: 0.0257 | Y34: 0.0277 | Z34: 0.0277 | AA34: 0.0277 | AB34: 0.0277 | AC34: 0.0297 | AD34: 0.0297 | AE34: 0.0317 | AF34: 0.0317 | AG34: 0.0337 | AH34: 0.0337 | AI34: 0.0337 | AJ34: 0.0337 | AK34: 0.0317 | AL34: 0.0317 | AM34: 0.0317 | AN34: 0.0317 | AO34: 0.0297 | AP34: 0.0297 | AQ34: 0.0267 | AR34: 0.0267 | AS34: 0.026 | BA34: 1
C35: 42 | D35: 개월 | E35: 0.0062 | F35: 0.0062 | G35: 0.0082 | H35: 0.0082 | I35: 0.0102 | J35: 0.0102 | K35: 0.0152 | L35: 0.0152 | M35: 0.0182 | N35: 0.0182 | O35: 0.0212 | P35: 0.0212 | Q35: 0.0232 | R35: 0.0232 | S35: 0.0252 | T35: 0.0252 | U35: 0.0252 | V35: 0.0252 | W35: 0.0252 | X35: 0.0252 | Y35: 0.0272 | Z35: 0.0272 | AA35: 0.0272 | AB35: 0.0272 | AC35: 0.0292 | AD35: 0.0292 | AE35: 0.0312 | AF35: 0.0312 | AG35: 0.0332 | AH35: 0.0332 | AI35: 0.0332 | AJ35: 0.0332 | AK35: 0.0312 | AL35: 0.0312 | AM35: 0.0312 | AN35: 0.0312 | AO35: 0.0292 | AP35: 0.0292 | AQ35: 0.0262 | AR35: 0.0262 | AS35: 0.0232 | AT35: 0.0228 | BA35: 1
C36: 43 | D36: 개월 | E36: 0.0057 | F36: 0.0057 | G36: 0.0077 | H36: 0.0077 | I36: 0.0097 | J36: 0.0097 | K36: 0.0147 | L36: 0.0147 | M36: 0.0177 | N36: 0.0177 | O36: 0.0207 | P36: 0.0207 | Q36: 0.0227 | R36: 0.0227 | S36: 0.0247 | T36: 0.0247 | U36: 0.0247 | V36: 0.0247 | W36: 0.0247 | X36: 0.0247 | Y36: 0.0267 | Z36: 0.0267 | AA36: 0.0267 | AB36: 0.0267 | AC36: 0.0287 | AD36: 0.0287 | AE36: 0.0307 | AF36: 0.0307 | AG36: 0.0327 | AH36: 0.0327 | AI36: 0.0327 | AJ36: 0.0327 | AK36: 0.0307 | AL36: 0.0307 | AM36: 0.0307 | AN36: 0.0307 | AO36: 0.0287 | AP36: 0.0287 | AQ36: 0.0257 | AR36: 0.0257 | AS36: 0.0227 | AT36: 0.0227 | AU36: 0.0206 | BA36: 1
C37: 44 | D37: 개월 | E37: 0.00535 | F37: 0.00535 | G37: 0.00735 | H37: 0.00735 | I37: 0.00935 | J37: 0.00935 | K37: 0.01435 | L37: 0.01435 | M37: 0.01735 | N37: 0.01735 | O37: 0.02035 | P37: 0.02035 | Q37: 0.02235 | R37: 0.02235 | S37: 0.02435 | T37: 0.02435 | U37: 0.02435 | V37: 0.02435 | W37: 0.02435 | X37: 0.02435 | Y37: 0.02635 | Z37: 0.02635 | AA37: 0.02635 | AB37: 0.02635 | AC37: 0.02835 | AD37: 0.02835 | AE37: 0.03035 | AF37: 0.03035 | AG37: 0.03235 | AH37: 0.03235 | AI37: 0.03235 | AJ37: 0.03235 | AK37: 0.03035 | AL37: 0.03035 | AM37: 0.03035 | AN37: 0.03035 | AO37: 0.02835 | AP37: 0.02835 | AQ37: 0.02535 | AR37: 0.02535 | AS37: 0.02235 | AT37: 0.02235 | AU37: 0.01935 | AV37: 0.01595 | BA37: 1
C38: 45 | D38: 개월 | E38: 0.0049 | F38: 0.0049 | G38: 0.0069 | H38: 0.0069 | I38: 0.0089 | J38: 0.0089 | K38: 0.0139 | L38: 0.0139 | M38: 0.0169 | N38: 0.0169 | O38: 0.0199 | P38: 0.0199 | Q38: 0.0219 | R38: 0.0219 | S38: 0.0239 | T38: 0.0239 | U38: 0.0239 | V38: 0.0239 | W38: 0.0239 | X38: 0.0239 | Y38: 0.0259 | Z38: 0.0259 | AA38: 0.0259 | AB38: 0.0259 | AC38: 0.0279 | AD38: 0.0279 | AE38: 0.0299 | AF38: 0.0299 | AG38: 0.0319 | AH38: 0.0319 | AI38: 0.0319 | AJ38: 0.0319 | AK38: 0.0299 | AL38: 0.0299 | AM38: 0.0299 | AN38: 0.0299 | AO38: 0.0279 | AP38: 0.0279 | AQ38: 0.0249 | AR38: 0.0249 | AS38: 0.0219 | AT38: 0.0219 | AU38: 0.0189 | AV38: 0.0189 | AW38: 0.0164 | BA38: 1
C39: 46 | D39: 개월 | E39: 0.00455 | F39: 0.00455 | G39: 0.00655 | H39: 0.00655 | I39: 0.00855 | J39: 0.00855 | K39: 0.01355 | L39: 0.01355 | M39: 0.01655 | N39: 0.01655 | O39: 0.01955 | P39: 0.01955 | Q39: 0.02155 | R39: 0.02155 | S39: 0.02355 | T39: 0.02355 | U39: 0.02355 | V39: 0.02355 | W39: 0.02355 | X39: 0.02355 | Y39: 0.02555 | Z39: 0.02555 | AA39: 0.02555 | AB39: 0.02555 | AC39: 0.02755 | AD39: 0.02755 | AE39: 0.02955 | AF39: 0.02955 | AG39: 0.03155 | AH39: 0.03155 | AI39: 0.03155 | AJ39: 0.03155 | AK39: 0.02955 | AL39: 0.02955 | AM39: 0.02955 | AN39: 0.02955 | AO39: 0.02755 | AP39: 0.02755 | AQ39: 0.02455 | AR39: 0.02455 | AS39: 0.02155 | AT39: 0.02155 | AU39: 0.01855 | AV39: 0.01855 | AW39: 0.01655 | AX39: 0.01525 | BA39: 1
C40: 47 | D40: 개월 | E40: 0.0042 | F40: 0.0042 | G40: 0.0062 | H40: 0.0062 | I40: 0.0082 | J40: 0.0082 | K40: 0.0132 | L40: 0.0132 | M40: 0.0162 | N40: 0.0162 | O40: 0.0192 | P40: 0.0192 | Q40: 0.0212 | R40: 0.0212 | S40: 0.0232 | T40: 0.0232 | U40: 0.0232 | V40: 0.0232 | W40: 0.0232 | X40: 0.0232 | Y40: 0.0252 | Z40: 0.0252 | AA40: 0.0252 | AB40: 0.0252 | AC40: 0.0272 | AD40: 0.0272 | AE40: 0.0292 | AF40: 0.0292 | AG40: 0.0312 | AH40: 0.0312 | AI40: 0.0312 | AJ40: 0.0312 | AK40: 0.0292 | AL40: 0.0292 | AM40: 0.0292 | AN40: 0.0292 | AO40: 0.0272 | AP40: 0.0272 | AQ40: 0.0242 | AR40: 0.0242 | AS40: 0.0212 | AT40: 0.0212 | AU40: 0.0182 | AV40: 0.0182 | AW40: 0.0162 | AX40: 0.0162 | AY40: 0.0148 | BA40: 1
C41: 48 | D41: 개월 | E41: 0.004 | F41: 0.004 | G41: 0.006 | H41: 0.006 | I41: 0.008 | J41: 0.008 | K41: 0.013 | L41: 0.013 | M41: 0.016 | N41: 0.016 | O41: 0.019 | P41: 0.019 | Q41: 0.021 | R41: 0.021 | S41: 0.023 | T41: 0.023 | U41: 0.023 | V41: 0.023 | W41: 0.023 | X41: 0.023 | Y41: 0.025 | Z41: 0.025 | AA41: 0.025 | AB41: 0.025 | AC41: 0.027 | AD41: 0.027 | AE41: 0.029 | AF41: 0.029 | AG41: 0.031 | AH41: 0.031 | AI41: 0.031 | AJ41: 0.031 | AK41: 0.029 | AL41: 0.029 | AM41: 0.029 | AN41: 0.029 | AO41: 0.027 | AP41: 0.027 | AQ41: 0.024 | AR41: 0.024 | AS41: 0.021 | AT41: 0.021 | AU41: 0.018 | AV41: 0.018 | AW41: 0.016 | AX41: 0.016 | AY41: 0.013 | AZ41: 0.011 | BA41: 1
